Workbook

Sheet CADASTRO DE MATERIAL
B2: CADASTRO DE MATERIAL & BALANÇO DE ESTOQUE
B3: Controle automático: Entradas, Saídas (Vendas por Item) e Saldo Atual em Estoque
B4: TOTAL GERAL: | F4: =SUM(F6:F500) -> 1244 | H4: =SUM(H6:H500) -> 85015.07
B5: ID / Código | C5: Produto e Tamanho (Unificado) | D5: Qtd Entrou (Inicial/Compras) | E5: Qtd Vendida (Baixa Automática) | F5: Saldo Atual em Estoque | G5: Custo Unitário (R$) | H5: Valor em Estoque (R$) | I5: Markup (%) | J5: Preço de Venda Sugerido (R$)
B6: EST-001 | C6: Tapete - 60x60 | D6: 2 | E6: =IF(ISBLANK(C6),"",SUMIF('SAÍDA DE VENDAS'!$G$6:$G$500, C6, 'SAÍDA DE VENDAS'!$H$6:$H$500)) -> 0 | F6: =IF(ISBLANK(C6),"", D6-E6) -> 2 | G6: 35 | H6: =IF(OR(ISBLANK(F6),ISBLANK(G6)), "", F6*G6) -> 70 | I6: 1 | J6: =IF(OR(ISBLANK(G6),ISBLANK(I6)), "", G6*(1+I6)) -> 70
B7: EST-002 | C7: TOALHA ROSTO SUPER SOFT ARABESCO ZERO TWIST CORTEX 50X70 | D7: =11*8 -> 88 | E7: =IF(ISBLANK(C7),"",SUMIF('SAÍDA DE VENDAS'!$G$6:$G$500, C7, 'SAÍDA DE VENDAS'!$H$6:$H$500)) -> 0 | F7: =IF(ISBLANK(C7),"", D7-E7) -> 88 | G7: 13 | H7: =IF(OR(ISBLANK(F7),ISBLANK(G7)), "", F7*G7) -> 1144 | I7: 1 | J7: =IF(OR(ISBLANK(G7),ISBLANK(I7)), "", G7*(1+I7)) -> 26
B8: EST-003 | C8: TOALHA BANHAO SUPER SOFT ARABESCO ZERO TWIST CORTEX 1,50X80 | D8: =11*8 -> 88 | E8: =IF(ISBLANK(C8),"",SUMIF('SAÍDA DE VENDAS'!$G$6:$G$500, C8, 'SAÍDA DE VENDAS'!$H$6:$H$500)) -> 0 | F8: =IF(ISBLANK(C8),"", D8-E8) -> 88 | G8: 37 | H8: =IF(OR(ISBLANK(F8),ISBLANK(G8)), "", F8*G8) -> 3256 | I8: 1 | J8: =IF(OR(ISBLANK(G8),ISBLANK(I8)), "", G8*(1+I8)) -> 74
B9: EST-004 | C9: KIT LAVABO LUXO 2 PEÇA | D9: 1 | E9: =IF(ISBLANK(C9),"",SUMIF('SAÍDA DE VENDAS'!$G$6:$G$500, C9, 'SAÍDA DE VENDAS'!$H$6:$H$500)) -> 0 | F9: =IF(ISBLANK(C9),"", D9-E9) -> 1 | G9: 79.9 | H9: =IF(OR(ISBLANK(F9),ISBLANK(G9)), "", F9*G9) -> 79.9 | I9: 0 | J9: =IF(OR(ISBLANK(G9),ISBLANK(I9)), "", G9*(1+I9)) -> 79.9
B10: EST-005 | C10: KIT LAVABO COROA 2 PEÇAS | D10: 19 | E10: =IF(ISBLANK(C10),"",SUMIF('SAÍDA DE VENDAS'!$G$6:$G$500, C10, 'SAÍDA DE VENDAS'!$H$6:$H$500)) -> 0 | F10: =IF(ISBLANK(C10),"", D10-E10) -> 19 | G10: 59.9 | H10: =IF(OR(ISBLANK(F10),ISBLANK(G10)), "", F10*G10) -> 1138.1 | I10: 0 | J10: =IF(OR(ISBLANK(G10),ISBLANK(I10)), "", G10*(1+I10)) -> 59.9
B11: EST-006 | C11: KIT LAVABO SIMPLES 2 PEÇAS | D11: 3 | E11: =IF(ISBLANK(C11),"",SUMIF('SAÍDA DE VENDAS'!$G$6:$G$500, C11, 'SAÍDA DE VENDAS'!$H$6:$H$500)) -> 0 | F11: =IF(ISBLANK(C11),"", D11-E11) -> 3 | G11: 49.9 | H11: =IF(OR(ISBLANK(F11),ISBLANK(G11)), "", F11*G11) -> 149.7 | I11: 0 | J11: =IF(OR(ISBLANK(G11),ISBLANK(I11)), "", G11*(1+I11)) -> 49.9
B12: EST-007 | C12: JOGO AMERICANO MALHA 7 PEÇAS | D12: 4 | E12: =IF(ISBLANK(C12),"",SUMIF('SAÍDA DE VENDAS'!$G$6:$G$500, C12, 'SAÍDA DE VENDAS'!$H$6:$H$500)) -> 0 | F12: =IF(ISBLANK(C12),"", D12-E12) -> 4 | G12: 109.9 | H12: =IF(OR(ISBLANK(F12),ISBLANK(G12)), "", F12*G12) -> 439.6 | I12: 0 | J12: =IF(OR(ISBLANK(G12),ISBLANK(I12)), "", G12*(1+I12)) -> 109.9
B13: EST-008 | C13: JOGO AMERICANO LINHA 7 PEÇAS | D13: 9 | E13: =IF(ISBLANK(C13),"",SUMIF('SAÍDA DE VENDAS'!$G$6:$G$500, C13, 'SAÍDA DE VENDAS'!$H$6:$H$500)) -> 0 | F13: =IF(ISBLANK(C13),"", D13-E13) -> 9 | G13: 49.9 | H13: =IF(OR(ISBLANK(F13),ISBLANK(G13)), "", F13*G13) -> 449.1 | I13: 0 | J13: =IF(OR(ISBLANK(G13),ISBLANK(I13)), "", G13*(1+I13)) -> 49.9
B14: EST-009 | C14: JOGO AMERICANO COMPLETO 18 PEÇAS | D14: 11 | E14: =IF(ISBLANK(C14),"",SUMIF('SAÍDA DE VENDAS'!$G$6:$G$500, C14, 'SAÍDA DE VENDAS'!$H$6:$H$500)) -> 0 | F14: =IF(ISBLANK(C14),"", D14-E14) -> 11 | G14: 129.9 | H14: =IF(OR(ISBLANK(F14),ISBLANK(G14)), "", F14*G14) -> 1428.9 | I14: 0 | J14: =IF(OR(ISBLANK(G14),ISBLANK(I14)), "", G14*(1+I14)) -> 129.9
B15: EST-010 | C15: JOGO AMERICANO COMPLETO 12 PEÇAS | D15: 2 | E15: =IF(ISBLANK(C15),"",SUMIF('SAÍDA DE VENDAS'!$G$6:$G$500, C15, 'SAÍDA DE VENDAS'!$H$6:$H$500)) -> 0 | F15: =IF(ISBLANK(C15),"", D15-E15) -> 2 | G15: 89.9 | H15: =IF(OR(ISBLANK(F15),ISBLANK(G15)), "", F15*G15) -> 179.8 | I15: 0 | J15: =IF(OR(ISBLANK(G15),ISBLANK(I15)), "", G15*(1+I15)) -> 89.9
B16: EST-011 | C16: JO0GO AMERICANO LINHA 18 PEÇAS | D16: 1 | E16: =IF(ISBLANK(C16),"",SUMIF('SAÍDA DE VENDAS'!$G$6:$G$500, C16, 'SAÍDA DE VENDAS'!$H$6:$H$500)) -> 0 | F16: =IF(ISBLANK(C16),"", D16-E16) -> 1 | G16: 89.9 | H16: =IF(OR(ISBLANK(F16),ISBLANK(G16)), "", F16*G16) -> 89.9 | I16: 0 | J16: =IF(OR(ISBLANK(G16),ISBLANK(I16)), "", G16*(1+I16)) -> 89.9
B17: EST-012 | C17: KIT COBRE LANCHES 2 PEÇAS | D17: 2 | E17: =IF(ISBLANK(C17),"",SUMIF('SAÍDA DE VENDAS'!$G$6:$G$500, C17, 'SAÍDA DE VENDAS'!$H$6:$H$500)) -> 0 | F17: =IF(ISBLANK(C17),"", D17-E17) -> 2 | G17: 109.9 | H17: =IF(OR(ISBLANK(F17),ISBLANK(G17)), "", F17*G17) -> 219.8 | I17: 0 | J17: =IF(OR(ISBLANK(G17),ISBLANK(I17)), "", G17*(1+I17)) -> 109.9
B18: EST-013 | C18: LUGAR AMERICANO | D18: 16 | E18: =IF(ISBLANK(C18),"",SUMIF('SAÍDA DE VENDAS'!$G$6:$G$500, C18, 'SAÍDA DE VENDAS'!$H$6:$H$500)) -> 0 | F18: =IF(ISBLANK(C18),"", D18-E18) -> 16 | G18: 13.9 | H18: =IF(OR(ISBLANK(F18),ISBLANK(G18)), "", F18*G18) -> 222.4 | I18: 0 | J18: =IF(OR(ISBLANK(G18),ISBLANK(I18)), "", G18*(1+I18)) -> 13.9
B19: EST-014 | C19: JOGO AMERICANO 4 LUGARES | D19: 1 | E19: =IF(ISBLANK(C19),"",SUMIF('SAÍDA DE VENDAS'!$G$6:$G$500, C19, 'SAÍDA DE VENDAS'!$H$6:$H$500)) -> 0 | F19: =IF(ISBLANK(C19),"", D19-E19) -> 1 | G19: 109.09 | H19: =IF(OR(ISBLANK(F19),ISBLANK(G19)), "", F19*G19) -> 109.09 | I19: 0 | J19: =IF(OR(ISBLANK(G19),ISBLANK(I19)), "", G19*(1+I19)) -> 109.09
B20: EST-015 | C20: LUGAR AMERICANO | D20: 14 | E20: =IF(ISBLANK(C20),"",SUMIF('SAÍDA DE VENDAS'!$G$6:$G$500, C20, 'SAÍDA DE VENDAS'!$H$6:$H$500)) -> 0 | F20: =IF(ISBLANK(C20),"", D20-E20) -> 14 | G20: 9.9 | H20: =IF(OR(ISBLANK(F20),ISBLANK(G20)), "", F20*G20) -> 138.6 | I20: 0 | J20: =IF(OR(ISBLANK(G20),ISBLANK(I20)), "", G20*(1+I20)) -> 9.9
... B63: EST-058 | C63: TOALHA BANHAO JACAR 1,20X80 | D63: 6 | E63: =IF(ISBLANK(C63),"",SUMIF('SAÍDA DE VENDAS'!$G$6:$G$500, C63, 'SAÍDA DE VENDAS'!$H$6:$H$500)) -> 0 | F63: =IF(ISBLANK(C63),"", D63-E63) -> 6 | G63: 59.9 | H63: =IF(OR(ISBLANK(F63),ISBLANK(G63)), "", F63*G63) -> 359.4 | I63: 0 | J63: =IF(OR(ISBLANK(G63),ISBLANK(I63)), "", G63*(1+I63)) -> 59.9
B64: EST-059 | C64: TOALHA DE ROSTO JACAR 50X70 | D64: =9+8 -> 17 | E64: =IF(ISBLANK(C64),"",SUMIF('SAÍDA DE VENDAS'!$G$6:$G$500, C64, 'SAÍDA DE VENDAS'!$H$6:$H$500)) -> 0 | F64: =IF(ISBLANK(C64),"", D64-E64) -> 17 | G64: 25 | H64: =IF(OR(ISBLANK(F64),ISBLANK(G64)), "", F64*G64) -> 425 | I64: 0 | J64: =IF(OR(ISBLANK(G64),ISBLANK(I64)), "", G64*(1+I64)) -> 25
B65: EST-060 | C65: TAPETE INDIANO 1,98X2,48 | D65: 1 | E65: =IF(ISBLANK(C65),"",SUMIF('SAÍDA DE VENDAS'!$G$6:$G$500, C65, 'SAÍDA DE VENDAS'!$H$6:$H$500)) -> 0 | F65: =IF(ISBLANK(C65),"", D65-E65) -> 1 | G65: 589.9 | H65: =IF(OR(ISBLANK(F65),ISBLANK(G65)), "", F65*G65) -> 589.9 | I65: 0 | J65: =IF(OR(ISBLANK(G65),ISBLANK(I65)), "", G65*(1+I65)) -> 589.9
B66: EST-061 | C66: TAPETE MOLDURA MALHA 1,50X2,0 | D66: 9 | E66: =IF(ISBLANK(C66),"",SUMIF('SAÍDA DE VENDAS'!$G$6:$G$500, C66, 'SAÍDA DE VENDAS'!$H$6:$H$500)) -> 0 | F66: =IF(ISBLANK(C66),"", D66-E66) -> 9 | G66: 209.9 | H66: =IF(OR(ISBLANK(F66),ISBLANK(G66)), "", F66*G66) -> 1889.1 | I66: 0 | J66: =IF(OR(ISBLANK(G66),ISBLANK(I66)), "", G66*(1+I66)) -> 209.9
B67: EST-062 | C67: TAPETE MALHA INCA 2,0X1,50 | D67: 2 | E67: =IF(ISBLANK(C67),"",SUMIF('SAÍDA DE VENDAS'!$G$6:$G$500, C67, 'SAÍDA DE VENDAS'!$H$6:$H$500)) -> 0 | F67: =IF(ISBLANK(C67),"", D67-E67) -> 2 | G67: 259.9 | H67: =IF(OR(ISBLANK(F67),ISBLANK(G67)), "", F67*G67) -> 519.8 | I67: 0 | J67: =IF(OR(ISBLANK(G67),ISBLANK(I67)), "", G67*(1+I67)) -> 259.9
B68: EST-063 | C68: TAPETE MALHA LISTRA 1,50X2,0 | D68: 1 | E68: =IF(ISBLANK(C68),"",SUMIF('SAÍDA DE VENDAS'!$G$6:$G$500, C68, 'SAÍDA DE VENDAS'!$H$6:$H$500)) -> 0 | F68: =IF(ISBLANK(C68),"", D68-E68) -> 1 | G68: 239.9 | H68: =IF(OR(ISBLANK(F68),ISBLANK(G68)), "", F68*G68) -> 239.9 | I68: 0 | J68: =IF(OR(ISBLANK(G68),ISBLANK(I68)), "", G68*(1+I68)) -> 239.9
B69: EST-064 | C69: TAPETE ALGODAO LINHA 1,50X2,0 | D69: 1 | E69: =IF(ISBLANK(C69),"",SUMIF('SAÍDA DE VENDAS'!$G$6:$G$500, C69, 'SAÍDA DE VENDAS'!$H$6:$H$500)) -> 0 | F69: =IF(ISBLANK(C69),"", D69-E69) -> 1 | G69: 299.9 | H69: =IF(OR(ISBLANK(F69),ISBLANK(G69)), "", F69*G69) -> 299.9 | I69: 0 | J69: =IF(OR(ISBLANK(G69),ISBLANK(I69)), "", G69*(1+I69)) -> 299.9
B70: EST-065 | C70: TAPETE TRAMPA CHIQUE 1,50X2,0 | D70: 1 | E70: =IF(ISBLANK(C70),"",SUMIF('SAÍDA DE VENDAS'!$G$6:$G$500, C70, 'SAÍDA DE VENDAS'!$H$6:$H$500)) -> 0 | F70: =IF(ISBLANK(C70),"", D70-E70) -> 1 | G70: 289.9 | H70: =IF(OR(ISBLANK(F70),ISBLANK(G70)), "", F70*G70) -> 289.9 | I70: 0 | J70: =IF(OR(ISBLANK(G70),ISBLANK(I70)), "", G70*(1+I70)) -> 289.9
B71: EST-066 | C71: TAPETE TRAMA 1,50X2,0 | D71: 1 | E71: =IF(ISBLANK(C71),"",SUMIF('SAÍDA DE VENDAS'!$G$6:$G$500, C71, 'SAÍDA DE VENDAS'!$H$6:$H$500)) -> 0 | F71: =IF(ISBLANK(C71),"", D71-E71) -> 1 | G71: 259.9 | H71: =IF(OR(ISBLANK(F71),ISBLANK(G71)), "", F71*G71) -> 259.9 | I71: 0 | J71: =IF(OR(ISBLANK(G71),ISBLANK(I71)), "", G71*(1+I71)) -> 259.9
B72: EST-067 | C72: TAPETE MALHA INCA 1,50X1,50 | D72: 1 | E72: =IF(ISBLANK(C72),"",SUMIF('SAÍDA DE VENDAS'!$G$6:$G$500, C72, 'SAÍDA DE VENDAS'!$H$6:$H$500)) -> 0 | F72: =IF(ISBLANK(C72),"", D72-E72) -> 1 | G72: 189.9 | H72: =IF(OR(ISBLANK(F72),ISBLANK(G72)), "", F72*G72) -> 189.9 | I72: 0 | J72: =IF(OR(ISBLANK(G72),ISBLANK(I72)), "", G72*(1+I72)) -> 189.9
B73: EST-068 | C73: TAPETE MALHA INCA COLORIDO 1,5X2,0 | D73: 2 | E73: =IF(ISBLANK(C73),"",SUMIF('SAÍDA DE VENDAS'!$G$6:$G$500, C73, 'SAÍDA DE VENDAS'!$H$6:$H$500)) -> 0 | F73: =IF(ISBLANK(C73),"", D73-E73) -> 2 | G73: 329.9 | H73: =IF(OR(ISBLANK(F73),ISBLANK(G73)), "", F73*G73) -> 659.8 | I73: 0 | J73: =IF(OR(ISBLANK(G73),ISBLANK(I73)), "", G73*(1+I73)) -> 329.9
B74: EST-069 | C74: MANTA COMUM 1,2X1,80 | D74: 4 | E74: =IF(ISBLANK(C74),"",SUMIF('SAÍDA DE VENDAS'!$G$6:$G$500, C74, 'SAÍDA DE VENDAS'!$H$6:$H$500)) -> 0 | F74: =IF(ISBLANK(C74),"", D74-E74) -> 4 | G74: 69.9 | H74: =IF(OR(ISBLANK(F74),ISBLANK(G74)), "", F74*G74) -> 279.6 | I74: 0 | J74: =IF(OR(ISBLANK(G74),ISBLANK(I74)), "", G74*(1+I74)) -> 69.9
B75: EST-070 | C75: MANTA CHEMILE 1,2X1,80 | D75: 2 | E75: =IF(ISBLANK(C75),"",SUMIF('SAÍDA DE VENDAS'!$G$6:$G$500, C75, 'SAÍDA DE VENDAS'!$H$6:$H$500)) -> 0 | F75: =IF(ISBLANK(C75),"", D75-E75) -> 2 | G75: 159.9 | H75: =IF(OR(ISBLANK(F75),ISBLANK(G75)), "", F75*G75) -> 319.8 | I75: 0 | J75: =IF(OR(ISBLANK(G75),ISBLANK(I75)), "", G75*(1+I75)) -> 159.9
B76: EST-071 | C76: MANTA ESCAMA 1,20X1,80 | D76: 4 | E76: =IF(ISBLANK(C76),"",SUMIF('SAÍDA DE VENDAS'!$G$6:$G$500, C76, 'SAÍDA DE VENDAS'!$H$6:$H$500)) -> 0 | F76: =IF(ISBLANK(C76),"", D76-E76) -> 4 | G76: 119.9 | H76: =IF(OR(ISBLANK(F76),ISBLANK(G76)), "", F76*G76) -> 479.6 | I76: 0 | J76: =IF(OR(ISBLANK(G76),ISBLANK(I76)), "", G76*(1+I76)) -> 119.9
... B122: EST-117 | C122: TAPETE DADO 50X80 | D122: 7 | E122: =IF(ISBLANK(C122),"",SUMIF('SAÍDA DE VENDAS'!$G$6:$G$500, C122, 'SAÍDA DE VENDAS'!$H$6:$H$500)) -> 0 | F122: =IF(ISBLANK(C122),"", D122-E122) -> 7 | G122: 39.9 | H122: =IF(OR(ISBLANK(F122),ISBLANK(G122)), "", F122*G122) -> 279.3 | I122: 0 | J122: =IF(OR(ISBLANK(G122),ISBLANK(I122)), "", G122*(1+I122)) -> 39.9
B123: EST-118 | C123: PAR TAPETE MALHA 50X80 | D123: =25 -> 25 | E123: =IF(ISBLANK(C123),"",SUMIF('SAÍDA DE VENDAS'!$G$6:$G$500, C123, 'SAÍDA DE VENDAS'!$H$6:$H$500)) -> 2 | F123: =IF(ISBLANK(C123),"", D123-E123) -> 23 | G123: 49.9 | H123: =IF(OR(ISBLANK(F123),ISBLANK(G123)), "", F123*G123) -> 1147.7 | I123: 0 | J123: =IF(OR(ISBLANK(G123),ISBLANK(I123)), "", G123*(1+I123)) -> 49.9
B124: EST-119 | C124: KIT LENÇOL MALHA QUEEN | D124: 2 | E124: =IF(ISBLANK(C124),"",SUMIF('SAÍDA DE VENDAS'!$G$6:$G$500, C124, 'SAÍDA DE VENDAS'!$H$6:$H$500)) -> 0 | F124: =IF(ISBLANK(C124),"", D124-E124) -> 2 | G124: 116 | H124: =IF(OR(ISBLANK(F124),ISBLANK(G124)), "", F124*G124) -> 232 | I124: 0 | J124: =IF(OR(ISBLANK(G124),ISBLANK(I124)), "", G124*(1+I124)) -> 116
B125: EST-120 | C125: KIT LAVABO FLORZINHA 2 PEÇAS | D125: 1 | E125: =IF(ISBLANK(C125),"",SUMIF('SAÍDA DE VENDAS'!$G$6:$G$500, C125, 'SAÍDA DE VENDAS'!$H$6:$H$500)) -> 0 | F125: =IF(ISBLANK(C125),"", D125-E125) -> 1 | G125: 59.9 | H125: =IF(OR(ISBLANK(F125),ISBLANK(G125)), "", F125*G125) -> 59.9 | I125: 0 | J125: =IF(OR(ISBLANK(G125),ISBLANK(I125)), "", G125*(1+I125)) -> 59.9
B126: EST-121 | C126: TOALHA PARA LAVABO | D126: 31 | E126: =IF(ISBLANK(C126),"",SUMIF('SAÍDA DE VENDAS'!$G$6:$G$500, C126, 'SAÍDA DE VENDAS'!$H$6:$H$500)) -> 0 | F126: =IF(ISBLANK(C126),"", D126-E126) -> 31 | G126: 15.5 | H126: =IF(OR(ISBLANK(F126),ISBLANK(G126)), "", F126*G126) -> 480.5 | I126: 0 | J126: =IF(OR(ISBLANK(G126),ISBLANK(I126)), "", G126*(1+I126)) -> 15.5
B127: EST-122 | C127: COBERTA SOFT QUEEN | D127: 8 | E127: =IF(ISBLANK(C127),"",SUMIF('SAÍDA DE VENDAS'!$G$6:$G$500, C127, 'SAÍDA DE VENDAS'!$H$6:$H$500)) -> 0 | F127: =IF(ISBLANK(C127),"", D127-E127) -> 8 | G127: 69.9 | H127: =IF(OR(ISBLANK(F127),ISBLANK(G127)), "", F127*G127) -> 559.2 | I127: 0 | J127: =IF(OR(ISBLANK(G127),ISBLANK(I127)), "", G127*(1+I127)) -> 69.9
B128: EST-123 | C128: COBERTA SOFT CASAL | D128: 16 | E128: =IF(ISBLANK(C128),"",SUMIF('SAÍDA DE VENDAS'!$G$6:$G$500, C128, 'SAÍDA DE VENDAS'!$H$6:$H$500)) -> 0 | F128: =IF(ISBLANK(C128),"", D128-E128) -> 16 | G128: 59.9 | H128: =IF(OR(ISBLANK(F128),ISBLANK(G128)), "", F128*G128) -> 958.4 | I128: 0 | J128: =IF(OR(ISBLANK(G128),ISBLANK(I128)), "", G128*(1+I128)) -> 59.9
B129: EST-124 | C129: REFIL AMOFADA 45X45 | D129: 32 | E129: =IF(ISBLANK(C129),"",SUMIF('SAÍDA DE VENDAS'!$G$6:$G$500, C129, 'SAÍDA DE VENDAS'!$H$6:$H$500)) -> 0 | F129: =IF(ISBLANK(C129),"", D129-E129) -> 32 | G129: 25 | H129: =IF(OR(ISBLANK(F129),ISBLANK(G129)), "", F129*G129) -> 800 | I129: 0 | J129: =IF(OR(ISBLANK(G129),ISBLANK(I129)), "", G129*(1+I129)) -> 25
B130: EST-125 | C130: CAPAS ALMOFADAS BORDADAS 45X45 | D130: 13 | E130: =IF(ISBLANK(C130),"",SUMIF('SAÍDA DE VENDAS'!$G$6:$G$500, C130, 'SAÍDA DE VENDAS'!$H$6:$H$500)) -> 0 | F130: =IF(ISBLANK(C130),"", D130-E130) -> 13 | G130: 89.9 | H130: =IF(OR(ISBLANK(F130),ISBLANK(G130)), "", F130*G130) -> 1168.7 | I130: 0 | J130: =IF(OR(ISBLANK(G130),ISBLANK(I130)), "", G130*(1+I130)) -> 89.9
B131: EST-126 | C131: CAPAS ALMOFADAS LINHA 45X45 | D131: 3 | E131: =IF(ISBLANK(C131),"",SUMIF('SAÍDA DE VENDAS'!$G$6:$G$500, C131, 'SAÍDA DE VENDAS'!$H$6:$H$500)) -> 0 | F131: =IF(ISBLANK(C131),"", D131-E131) -> 3 | G131: 49.9 | H131: =IF(OR(ISBLANK(F131),ISBLANK(G131)), "", F131*G131) -> 149.7 | I131: 0 | J131: =IF(OR(ISBLANK(G131),ISBLANK(I131)), "", G131*(1+I131)) -> 49.9
B132: EST-127 | C132: CAPAS ALMOFADAS CHENILE 45X45 | D132: 2 | E132: =IF(ISBLANK(C132),"",SUMIF('SAÍDA DE VENDAS'!$G$6:$G$500, C132, 'SAÍDA DE VENDAS'!$H$6:$H$500)) -> 0 | F132: =IF(ISBLANK(C132),"", D132-E132) -> 2 | G132: 59.9 | H132: =IF(OR(ISBLANK(F132),ISBLANK(G132)), "", F132*G132) -> 119.8 | I132: 0 | J132: =IF(OR(ISBLANK(G132),ISBLANK(I132)), "", G132*(1+I132)) -> 59.9
B133: EST-128 | C133: CAPAS ALMOFADAS ESCAMA 45X45 | D133: 5 | E133: =IF(ISBLANK(C133),"",SUMIF('SAÍDA DE VENDAS'!$G$6:$G$500, C133, 'SAÍDA DE VENDAS'!$H$6:$H$500)) -> 0 | F133: =IF(ISBLANK(C133),"", D133-E133) -> 5 | G133: 59.9 | H133: =IF(OR(ISBLANK(F133),ISBLANK(G133)), "", F133*G133) -> 299.5 | I133: 0 | J133: =IF(OR(ISBLANK(G133),ISBLANK(I133)), "", G133*(1+I133)) -> 59.9
B134: EST-129 | C134: CAPAS ALMOFADAS BUDE 45X45 | D134: 3 | E134: =IF(ISBLANK(C134),"",SUMIF('SAÍDA DE VENDAS'!$G$6:$G$500, C134, 'SAÍDA DE VENDAS'!$H$6:$H$500)) -> 0 | F134: =IF(ISBLANK(C134),"", D134-E134) -> 3 | G134: 49.9 | H134: =IF(OR(ISBLANK(F134),ISBLANK(G134)), "", F134*G134) -> 149.7 | I134: 0 | J134: =IF(OR(ISBLANK(G134),ISBLANK(I134)), "", G134*(1+I134)) -> 49.9
B135: EST-130 | C135: CAPAS ALMOFADAS GRIDE 45X45 | D135: 3 | E135: =IF(ISBLANK(C135),"",SUMIF('SAÍDA DE VENDAS'!$G$6:$G$500, C135, 'SAÍDA DE VENDAS'!$H$6:$H$500)) -> 0 | F135: =IF(ISBLANK(C135),"", D135-E135) -> 3 | G135: 44.9 | H135: =IF(OR(ISBLANK(F135),ISBLANK(G135)), "", F135*G135) -> 134.7 | I135: 0 | J135: =IF(OR(ISBLANK(G135),ISBLANK(I135)), "", G135*(1+I135)) -> 44.9
... B215: EST-210 | C215: JOGO PASSADEIRA BARRADO 1,50 | D215: 1 | E215: =IF(ISBLANK(C215),"",SUMIF('SAÍDA DE VENDAS'!$G$6:$G$500, C215, 'SAÍDA DE VENDAS'!$H$6:$H$500)) -> 0 | F215: =IF(ISBLANK(C215),"", D215-E215) -> 1 | G215: 159.9 | H215: =IF(OR(ISBLANK(F215),ISBLANK(G215)), "", F215*G215) -> 159.9 | I215: 0 | J215: =IF(OR(ISBLANK(G215),ISBLANK(I215)), "", G215*(1+I215)) -> 159.9
B216: EST-211 | C216: TAPETE FAXINHAS PREMIUM 50X80 | D216: 2 | E216: =IF(ISBLANK(C216),"",SUMIF('SAÍDA DE VENDAS'!$G$6:$G$500, C216, 'SAÍDA DE VENDAS'!$H$6:$H$500)) -> 0 | F216: =IF(ISBLANK(C216),"", D216-E216) -> 2 | H216: =IF(OR(ISBLANK(F216),ISBLANK(G216)), "", F216*G216) | I216: 0 | J216: =IF(OR(ISBLANK(G216),ISBLANK(I216)), "", G216*(1+I216))
B217: EST-212 | C217: PARES MALHA PREMIUIM 50X80 | D217: 8 | E217: =IF(ISBLANK(C217),"",SUMIF('SAÍDA DE VENDAS'!$G$6:$G$500, C217, 'SAÍDA DE VENDAS'!$H$6:$H$500)) -> 0 | F217: =IF(ISBLANK(C217),"", D217-E217) -> 8 | G217: 59.9 | H217: =IF(OR(ISBLANK(F217),ISBLANK(G217)), "", F217*G217) -> 479.2 | I217: 0 | J217: =IF(OR(ISBLANK(G217),ISBLANK(I217)), "", G217*(1+I217)) -> 59.9
B218: EST-213 | C218: PASSADEIRA SEDA 3 | D218: 4 | E218: =IF(ISBLANK(C218),"",SUMIF('SAÍDA DE VENDAS'!$G$6:$G$500, C218, 'SAÍDA DE VENDAS'!$H$6:$H$500)) -> 0 | F218: =IF(ISBLANK(C218),"", D218-E218) -> 4 | G218: 349.9 | H218: =IF(OR(ISBLANK(F218),ISBLANK(G218)), "", F218*G218) -> 1399.6 | I218: 0 | J218: =IF(OR(ISBLANK(G218),ISBLANK(I218)), "", G218*(1+I218)) -> 349.9
B219: EST-214 | C219: PASSADEIRA SEDA 2 | D219: 5 | E219: =IF(ISBLANK(C219),"",SUMIF('SAÍDA DE VENDAS'!$G$6:$G$500, C219, 'SAÍDA DE VENDAS'!$H$6:$H$500)) -> 1 | F219: =IF(ISBLANK(C219),"", D219-E219) -> 4 | G219: 239.9 | H219: =IF(OR(ISBLANK(F219),ISBLANK(G219)), "", F219*G219) -> 959.6 | I219: 0 | J219: =IF(OR(ISBLANK(G219),ISBLANK(I219)), "", G219*(1+I219)) -> 239.9
B220: EST-215 | C220: TAPETE FIO SEDA 50X80 | D220: 3 | E220: =IF(ISBLANK(C220),"",SUMIF('SAÍDA DE VENDAS'!$G$6:$G$500, C220, 'SAÍDA DE VENDAS'!$H$6:$H$500)) -> 0 | F220: =IF(ISBLANK(C220),"", D220-E220) -> 3 | G220: 35 | H220: =IF(OR(ISBLANK(F220),ISBLANK(G220)), "", F220*G220) -> 105 | I220: 0 | J220: =IF(OR(ISBLANK(G220),ISBLANK(I220)), "", G220*(1+I220)) -> 35
B221: EST-216 | C221: BEIRA CAMA RUSTICO 80X1,50 | D221: 8 | E221: =IF(ISBLANK(C221),"",SUMIF('SAÍDA DE VENDAS'!$G$6:$G$500, C221, 'SAÍDA DE VENDAS'!$H$6:$H$500)) -> 0 | F221: =IF(ISBLANK(C221),"", D221-E221) -> 8 | G221: 129.9 | H221: =IF(OR(ISBLANK(F221),ISBLANK(G221)), "", F221*G221) -> 1039.2 | I221: 0 | J221: =IF(OR(ISBLANK(G221),ISBLANK(I221)), "", G221*(1+I221)) -> 129.9
B222: EST-217 | C222: JOGO DUPLA FACE TRADICIONAL 1,50 | D222: 2 | E222: =IF(ISBLANK(C222),"",SUMIF('SAÍDA DE VENDAS'!$G$6:$G$500, C222, 'SAÍDA DE VENDAS'!$H$6:$H$500)) -> 0 | F222: =IF(ISBLANK(C222),"", D222-E222) -> 2 | G222: 169.9 | H222: =IF(OR(ISBLANK(F222),ISBLANK(G222)), "", F222*G222) -> 339.8 | I222: 0 | J222: =IF(OR(ISBLANK(G222),ISBLANK(I222)), "", G222*(1+I222)) -> 169.9
B223: EST-218 | C223: CAMINHO DE MESA 1,5 | D223: 2 | E223: =IF(ISBLANK(C223),"",SUMIF('SAÍDA DE VENDAS'!$G$6:$G$500, C223, 'SAÍDA DE VENDAS'!$H$6:$H$500)) -> 0 | F223: =IF(ISBLANK(C223),"", D223-E223) -> 2 | G223: 69.9 | H223: =IF(OR(ISBLANK(F223),ISBLANK(G223)), "", F223*G223) -> 139.8 | I223: 0 | J223: =IF(OR(ISBLANK(G223),ISBLANK(I223)), "", G223*(1+I223)) -> 69.9
B224: EST-219 | C224: CAMINHO DE MESA 2 | D224: 1 | E224: =IF(ISBLANK(C224),"",SUMIF('SAÍDA DE VENDAS'!$G$6:$G$500, C224, 'SAÍDA DE VENDAS'!$H$6:$H$500)) -> 0 | F224: =IF(ISBLANK(C224),"", D224-E224) -> 1 | G224: 89.9 | H224: =IF(OR(ISBLANK(F224),ISBLANK(G224)), "", F224*G224) -> 89.9 | I224: 0 | J224: =IF(OR(ISBLANK(G224),ISBLANK(I224)), "", G224*(1+I224)) -> 89.9
B225: EST-220 | C225: TAPETE INDIANO REDONDO 1,5 | D225: 2 | E225: =IF(ISBLANK(C225),"",SUMIF('SAÍDA DE VENDAS'!$G$6:$G$500, C225, 'SAÍDA DE VENDAS'!$H$6:$H$500)) -> 0 | F225: =IF(ISBLANK(C225),"", D225-E225) -> 2 | G225: 189.9 | H225: =IF(OR(ISBLANK(F225),ISBLANK(G225)), "", F225*G225) -> 379.8 | I225: 0 | J225: =IF(OR(ISBLANK(G225),ISBLANK(I225)), "", G225*(1+I225)) -> 189.9
B226: EST-221 | C226: PAR MALHA LISO 80X50 | D226: 4 | E226: =IF(ISBLANK(C226),"",SUMIF('SAÍDA DE VENDAS'!$G$6:$G$500, C226, 'SAÍDA DE VENDAS'!$H$6:$H$500)) -> 0 | F226: =IF(ISBLANK(C226),"", D226-E226) -> 4 | G226: 49.9 | H226: =IF(OR(ISBLANK(F226),ISBLANK(G226)), "", F226*G226) -> 199.6 | I226: 0 | J226: =IF(OR(ISBLANK(G226),ISBLANK(I226)), "", G226*(1+I226)) -> 49.9
B227: EST-222 | C227: CAPA ALMOFADA LINHO 45X45 | D227: 20 | E227: =IF(ISBLANK(C227),"",SUMIF('SAÍDA DE VENDAS'!$G$6:$G$500, C227, 'SAÍDA DE VENDAS'!$H$6:$H$500)) -> 0 | F227: =IF(ISBLANK(C227),"", D227-E227) -> 20 | G227: 39.9 | H227: =IF(OR(ISBLANK(F227),ISBLANK(G227)), "", F227*G227) -> 798 | I227: 0 | J227: =IF(OR(ISBLANK(G227),ISBLANK(I227)), "", G227*(1+I227)) -> 39.9
B228: EST-223 | C228: CAMINHO DE MESA LINHA 1,5 | D228: 4 | E228: =IF(ISBLANK(C228),"",SUMIF('SAÍDA DE VENDAS'!$G$6:$G$500, C228, 'SAÍDA DE VENDAS'!$H$6:$H$500)) -> 0 | F228: =IF(ISBLANK(C228),"", D228-E228) -> 4 | G228: 39.9 | H228: =IF(OR(ISBLANK(F228),ISBLANK(G228)), "", F228*G228) -> 159.6 | I228: 0 | J228: =IF(OR(ISBLANK(G228),ISBLANK(I228)), "", G228*(1+I228)) -> 39.9
... B244: EST-239 | C244: PESEIRA RELIQUIA ROSE 60X25 | D244: 1 | E244: =IF(ISBLANK(C244),"",SUMIF('SAÍDA DE VENDAS'!$G$6:$G$500, C244, 'SAÍDA DE VENDAS'!$H$6:$H$500)) -> 0 | F244: =IF(ISBLANK(C244),"", D244-E244) -> 1 | G244: 89.9 | H244: =IF(OR(ISBLANK(F244),ISBLANK(G244)), "", F244*G244) -> 89.9 | I244: 0 | J244: =IF(OR(ISBLANK(G244),ISBLANK(I244)), "", G244*(1+I244)) -> 89.9
B245: EST-240 | C245: CAPA ALMOFADAS RELIQUIA 45X45 | D245: =4+6+6+3 -> 19 | E245: =IF(ISBLANK(C245),"",SUMIF('SAÍDA DE VENDAS'!$G$6:$G$500, C245, 'SAÍDA DE VENDAS'!$H$6:$H$500)) -> 0 | F245: =IF(ISBLANK(C245),"", D245-E245) -> 19 | G245: 39.9 | H245: =IF(OR(ISBLANK(F245),ISBLANK(G245)), "", F245*G245) -> 758.1 | I245: 0 | J245: =IF(OR(ISBLANK(G245),ISBLANK(I245)), "", G245*(1+I245)) -> 39.9
B246: EST-241 | C246: PESEIRA RELIQUIA 60X2,5 | D246: 1 | E246: =IF(ISBLANK(C246),"",SUMIF('SAÍDA DE VENDAS'!$G$6:$G$500, C246, 'SAÍDA DE VENDAS'!$H$6:$H$500)) -> 0 | F246: =IF(ISBLANK(C246),"", D246-E246) -> 1 | G246: 89.9 | H246: =IF(OR(ISBLANK(F246),ISBLANK(G246)), "", F246*G246) -> 89.9 | I246: 0 | J246: =IF(OR(ISBLANK(G246),ISBLANK(I246)), "", G246*(1+I246)) -> 89.9
B247: EST-242 | C247: MANTA SOFT CASAL SIMPLES | D247: 40 | E247: =IF(ISBLANK(C247),"",SUMIF('SAÍDA DE VENDAS'!$G$6:$G$500, C247, 'SAÍDA DE VENDAS'!$H$6:$H$500)) -> 6 | F247: =IF(ISBLANK(C247),"", D247-E247) -> 34 | G247: 39.9 | H247: =IF(OR(ISBLANK(F247),ISBLANK(G247)), "", F247*G247) -> 1356.6 | I247: 0 | J247: =IF(OR(ISBLANK(G247),ISBLANK(I247)), "", G247*(1+I247)) -> 39.9
B248: EST-243 | E248: =IF(ISBLANK(C248),"",SUMIF('SAÍDA DE VENDAS'!$G$6:$G$500, C248, 'SAÍDA DE VENDAS'!$H$6:$H$500)) | F248: =IF(ISBLANK(C248),"", D248-E248) | H248: =IF(OR(ISBLANK(F248),ISBLANK(G248)), "", F248*G248) | I248: 0 | J248: =IF(OR(ISBLANK(G248),ISBLANK(I248)), "", G248*(1+I248))
B249: EST-244 | E249: =IF(ISBLANK(C249),"",SUMIF('SAÍDA DE VENDAS'!$G$6:$G$500, C249, 'SAÍDA DE VENDAS'!$H$6:$H$500)) | F249: =IF(ISBLANK(C249),"", D249-E249) | H249: =IF(OR(ISBLANK(F249),ISBLANK(G249)), "", F249*G249) | I249: 0 | J249: =IF(OR(ISBLANK(G249),ISBLANK(I249)), "", G249*(1+I249))
B250: EST-245 | E250: =IF(ISBLANK(C250),"",SUMIF('SAÍDA DE VENDAS'!$G$6:$G$500, C250, 'SAÍDA DE VENDAS'!$H$6:$H$500)) | F250: =IF(ISBLANK(C250),"", D250-E250) | H250: =IF(OR(ISBLANK(F250),ISBLANK(G250)), "", F250*G250) | I250: 0 | J250: =IF(OR(ISBLANK(G250),ISBLANK(I250)), "", G250*(1+I250))
B251: EST-246 | E251: =IF(ISBLANK(C251),"",SUMIF('SAÍDA DE VENDAS'!$G$6:$G$500, C251, 'SAÍDA DE VENDAS'!$H$6:$H$500)) | F251: =IF(ISBLANK(C251),"", D251-E251) | H251: =IF(OR(ISBLANK(F251),ISBLANK(G251)), "", F251*G251) | I251: 0 | J251: =IF(OR(ISBLANK(G251),ISBLANK(I251)), "", G251*(1+I251))
B252: EST-247 | E252: =IF(ISBLANK(C252),"",SUMIF('SAÍDA DE VENDAS'!$G$6:$G$500, C252, 'SAÍDA DE VENDAS'!$H$6:$H$500)) | F252: =IF(ISBLANK(C252),"", D252-E252) | H252: =IF(OR(ISBLANK(F252),ISBLANK(G252)), "", F252*G252) | I252: 0 | J252: =IF(OR(ISBLANK(G252),ISBLANK(I252)), "", G252*(1+I252))
B253: EST-248 | E253: =IF(ISBLANK(C253),"",SUMIF('SAÍDA DE VENDAS'!$G$6:$G$500, C253, 'SAÍDA DE VENDAS'!$H$6:$H$500)) | F253: =IF(ISBLANK(C253),"", D253-E253) | H253: =IF(OR(ISBLANK(F253),ISBLANK(G253)), "", F253*G253) | I253: 0 | J253: =IF(OR(ISBLANK(G253),ISBLANK(I253)), "", G253*(1+I253))
B254: EST-249 | E254: =IF(ISBLANK(C254),"",SUMIF('SAÍDA DE VENDAS'!$G$6:$G$500, C254, 'SAÍDA DE VENDAS'!$H$6:$H$500)) | F254: =IF(ISBLANK(C254),"", D254-E254) | H254: =IF(OR(ISBLANK(F254),ISBLANK(G254)), "", F254*G254) | I254: 0 | J254: =IF(OR(ISBLANK(G254),ISBLANK(I254)), "", G254*(1+I254))
B255: EST-250 | E255: =IF(ISBLANK(C255),"",SUMIF('SAÍDA DE VENDAS'!$G$6:$G$500, C255, 'SAÍDA DE VENDAS'!$H$6:$H$500)) | F255: =IF(ISBLANK(C255),"", D255-E255) | H255: =IF(OR(ISBLANK(F255),ISBLANK(G255)), "", F255*G255) | I255: 0 | J255: =IF(OR(ISBLANK(G255),ISBLANK(I255)), "", G255*(1+I255))
B256: EST-251 | E256: =IF(ISBLANK(C256),"",SUMIF('SAÍDA DE VENDAS'!$G$6:$G$500, C256, 'SAÍDA DE VENDAS'!$H$6:$H$500)) | F256: =IF(ISBLANK(C256),"", D256-E256) | H256: =IF(OR(ISBLANK(F256),ISBLANK(G256)), "", F256*G256) | I256: 0 | J256: =IF(OR(ISBLANK(G256),ISBLANK(I256)), "", G256*(1+I256))
B257: EST-252 | E257: =IF(ISBLANK(C257),"",SUMIF('SAÍDA DE VENDAS'!$G$6:$G$500, C257, 'SAÍDA DE VENDAS'!$H$6:$H$500)) | F257: =IF(ISBLANK(C257),"", D257-E257) | H257: =IF(OR(ISBLANK(F257),ISBLANK(G257)), "", F257*G257) | I257: 0 | J257: =IF(OR(ISBLANK(G257),ISBLANK(I257)), "", G257*(1+I257))
B258: EST-253 | E258: =IF(ISBLANK(C258),"",SUMIF('SAÍDA DE VENDAS'!$G$6:$G$500, C258, 'SAÍDA DE VENDAS'!$H$6:$H$500)) | F258: =IF(ISBLANK(C258),"", D258-E258) | H258: =IF(OR(ISBLANK(F258),ISBLANK(G258)), "", F258*G258) | I258: 0 | J258: =IF(OR(ISBLANK(G258),ISBLANK(I258)), "", G258*(1+I258))
B259: EST-254 | E259: =IF(ISBLANK(C259),"",SUMIF('SAÍDA DE VENDAS'!$G$6:$G$500, C259, 'SAÍDA DE VENDAS'!$H$6:$H$500)) | F259: =IF(ISBLANK(C259),"", D259-E259) | H259: =IF(OR(ISBLANK(F259),ISBLANK(G259)), "", F259*G259) | I259: 0 | J259: =IF(OR(ISBLANK(G259),ISBLANK(I259)), "", G259*(1+I259))
... B500: EST-495 | E500: =IF(ISBLANK(C500),"",SUMIF('SAÍDA DE VENDAS'!$G$6:$G$500, C500, 'SAÍDA DE VENDAS'!$H$6:$H$500)) | F500: =IF(ISBLANK(C500),"", D500-E500) | H500: =IF(OR(ISBLANK(F500),ISBLANK(G500)), "", F500*G500) | I500: 0 | J500: =IF(OR(ISBLANK(G500),ISBLANK(I500)), "", G500*(1+I500))

Sheet CADASTRO DE CLIENTES
B2: CADASTRO DE CLIENTES
B3: Base de dados de clientes para busca automática na aba Saída de Vendas
B5: ID Cliente | C5: Nome Completo do Cliente | D5: Endereço Completo | E5: Telefone / WhatsApp | F5: E-mail / Observações
B6: CLI-001 | C6: ADRIANA PEDRO | E6: 18 99818-0064
B7: CLI-002 | C7: VALERIA ALVES | E7: 18 93500-1704
B8: CLI-003 | C8: FLAVIA BEZERRA | E8: 18 99745-2150
B9: CLI-004 | C9: TELMA CAMPARI | E9: 18 99800-5512
B10: CLI-005 | C10: LUCIA HELENA | E10: 18 98205-2963
B11: CLI-006 | C11: CLAUDIA SILVA
B12: CLI-007 | C12: SONIA MARIA
B13: CLI-008 | C13: ROSE GALDINO
B14: CLI-009 | C14: HADIJA
B15: CLI-010 | C15: JULIANA CORREA
B16: CLI-011 | C16: DEIGILAN
B17: CLI-012 | C17: ANDREIA FERREIRA
B18: CLI-013 | C18: CLEIDE LOPES
B19: CLI-014 | C19: MADALENA UNIMED
B20: CLI-015 | C20: EDINA REGINA
B21: CLI-016 | C21: ROSI UNIMED
B22: CLI-017
B23: CLI-018
B24: CLI-019
B25: CLI-020
B26: CLI-021
B27: CLI-022
B28: CLI-023
B29: CLI-024
B30: CLI-025

Sheet SAÍDA DE VENDAS
B2: REGISTRO DE SAÍDA DE VENDAS (POR PEDIDO E ITEM)
B3: Adicione múltiplos itens no mesmo Pedido. O Valor Total do Pedido e o Resumo de Itens são calculados automaticamente.
B4: TOTAL VENDIDO: | H4: =SUM(H6:H500) -> 31 | J4: =SUM(J6:J500) -> 2528.9
B5: Nº Pedido | C5: ID Venda Item | D5: Data da Venda | E5: Nome do Cliente | F5: Telefone (Auto) | G5: Produto e Tamanho (Unificado) | H5: Qtd Vendida | I5: Valor Unitário (R$) | J5: Subtotal Item (R$) | K5: Condição do Pedido | L5: Valor de Entrada (R$) | M5: Saldo a Parcelar (R$) | N5: Total de Parcelas | O5: Total do Pedido (R$) | P5: Valor da Parcela (R$)
B6: PED-1001 | C6: V-001 | D6: 46298 | E6: ADRIANA PEDRO | F6: =IF(ISBLANK(E6),"",IFERROR(VLOOKUP(E6,'CADASTRO DE CLIENTES'!$C$6:$E$500,3,FALSE),"")) -> 18 99818-0064 | G6: KIT LENÇOL KING 2000 FIOS 3 PEÇAS | H6: 1 | I6: =IF(ISBLANK(G6),"",IFERROR(VLOOKUP(G6,'CADASTRO DE MATERIAL'!$C$6:$J$500,8,FALSE),"")) -> 139.9 | J6: =IF(OR(ISBLANK(H6),ISBLANK(I6)), "", H6*I6) -> 139.9 | K6: À Vista | L6: =IF(ISBLANK(B6), "", IF(K6="À Vista", O6, 0)) -> 139.9 | M6: =IF(ISBLANK(B6),"", O6 - IF(ISBLANK(L6), 0, L6)) -> 0 | N6: 1 | O6: =IF(ISBLANK(B6),"", SUMIF($B$6:$B$500, B6, $J$6:$J$500)) -> 139.9 | P6: =IF(OR(ISBLANK(M6),ISBLANK(N6),N6=0), "", M6/N6) -> 0
B7: =IF(AND(ISBLANK(D7), ISBLANK(E7), ISBLANK(G7)), "", IF(AND(E7<>"", E7=E6, D7<>"", D7=D6), B6, "PED-" & TEXT(IFERROR(VALUE(RIGHT(LOOKUP("PED-9999",$B$5:B6),4)),1000)+1, "0000"))) -> PED-1002 | C7: V-002 | D7: 46298 | E7: VALERIA ALVES | F7: =IF(ISBLANK(E7),"",IFERROR(VLOOKUP(E7,'CADASTRO DE CLIENTES'!$C$6:$E$500,3,FALSE),"")) -> 18 93500-1704 | G7: MANTA KING ALGODAO 2,45X2,85 | H7: 1 | I7: =IF(ISBLANK(G7),"",IFERROR(VLOOKUP(G7,'CADASTRO DE MATERIAL'!$C$6:$J$500,8,FALSE),"")) -> 139.9 | J7: =IF(OR(ISBLANK(H7),ISBLANK(I7)), "", H7*I7) -> 139.9 | K7: À Vista | L7: =IF(ISBLANK(B7), "", IF(K7="À Vista", O7, 0)) -> 139.9 | M7: =IF(ISBLANK(B7),"", O7 - IF(ISBLANK(L7), 0, L7)) -> 0 | N7: 1 | O7: =IF(ISBLANK(B7),"", SUMIF($B$6:$B$500, B7, $J$6:$J$500)) -> 139.9 | P7: =IF(OR(ISBLANK(M7),ISBLANK(N7),N7=0), "", M7/N7) -> 0
B8: =IF(AND(ISBLANK(D8), ISBLANK(E8), ISBLANK(G8)), "", IF(AND(E8<>"", E8=E7, D8<>"", D8=D7), B7, "PED-" & TEXT(IFERROR(VALUE(RIGHT(LOOKUP("PED-9999",$B$5:B7),4)),1000)+1, "0000"))) -> PED-1003 | C8: V-003 | D8: 46298 | E8: FLAVIA BEZERRA | F8: =IF(ISBLANK(E8),"",IFERROR(VLOOKUP(E8,'CADASTRO DE CLIENTES'!$C$6:$E$500,3,FALSE),"")) -> 18 99745-2150 | G8: PASSADEIRA PIPOQUINHA 50X2,0 | H8: 1 | I8: =IF(ISBLANK(G8),"",IFERROR(VLOOKUP(G8,'CADASTRO DE MATERIAL'!$C$6:$J$500,8,FALSE),"")) -> 149.9 | J8: =IF(OR(ISBLANK(H8),ISBLANK(I8)), "", H8*I8) -> 149.9 | K8: À Vista | L8: =IF(ISBLANK(B8), "", IF(K8="À Vista", O8, 0)) -> 149.9 | M8: =IF(ISBLANK(B8),"", O8 - IF(ISBLANK(L8), 0, L8)) -> 0 | N8: 1 | O8: =IF(ISBLANK(B8),"", SUMIF($B$6:$B$500, B8, $J$6:$J$500)) -> 149.9 | P8: =IF(OR(ISBLANK(M8),ISBLANK(N8),N8=0), "", M8/N8) -> 0
B9: =IF(AND(ISBLANK(D9), ISBLANK(E9), ISBLANK(G9)), "", IF(AND(E9<>"", E9=E8, D9<>"", D9=D8), B8, "PED-" & TEXT(IFERROR(VALUE(RIGHT(LOOKUP("PED-9999",$B$5:B8),4)),1000)+1, "0000"))) -> PED-1004 | C9: V-004 | D9: 46300 | E9: TELMA CAMPARI | F9: =IF(ISBLANK(E9),"",IFERROR(VLOOKUP(E9,'CADASTRO DE CLIENTES'!$C$6:$E$500,3,FALSE),"")) -> 18 99800-5512 | G9: MANTA SOFT CASAL SIMPLES | H9: 1 | I9: =IF(ISBLANK(G9),"",IFERROR(VLOOKUP(G9,'CADASTRO DE MATERIAL'!$C$6:$J$500,8,FALSE),"")) -> 39.9 | J9: =IF(OR(ISBLANK(H9),ISBLANK(I9)), "", H9*I9) -> 39.9 | K9: A Prazo | L9: =IF(ISBLANK(B9), "", IF(K9="À Vista", O9, 0)) -> 0 | M9: =IF(ISBLANK(B9),"", O9 - IF(ISBLANK(L9), 0, L9)) -> 39.9 | N9: 1 | O9: =IF(ISBLANK(B9),"", SUMIF($B$6:$B$500, B9, $J$6:$J$500)) -> 39.9 | P9: =IF(OR(ISBLANK(M9),ISBLANK(N9),N9=0), "", M9/N9) -> 39.9
B10: =IF(AND(ISBLANK(D10), ISBLANK(E10), ISBLANK(G10)), "", IF(AND(E10<>"", E10=E9, D10<>"", D10=D9), B9, "PED-" & TEXT(IFERROR(VALUE(RIGHT(LOOKUP("PED-9999",$B$5:B9),4)),1000)+1, "0000"))) -> PED-1005 | C10: V-005 | D10: 46300 | E10: ADRIANA PEDRO | F10: =IF(ISBLANK(E10),"",IFERROR(VLOOKUP(E10,'CADASTRO DE CLIENTES'!$C$6:$E$500,3,FALSE),"")) -> 18 99818-0064 | G10: MANTA SOFT CASAL SIMPLES | H10: 2 | I10: =IF(ISBLANK(G10),"",IFERROR(VLOOKUP(G10,'CADASTRO DE MATERIAL'!$C$6:$J$500,8,FALSE),"")) -> 39.9 | J10: =IF(OR(ISBLANK(H10),ISBLANK(I10)), "", H10*I10) -> 79.8 | K10: À Vista | L10: =IF(ISBLANK(B10), "", IF(K10="À Vista", O10, 0)) -> 79.8 | M10: =IF(ISBLANK(B10),"", O10 - IF(ISBLANK(L10), 0, L10)) -> 0 | N10: 1 | O10: =IF(ISBLANK(B10),"", SUMIF($B$6:$B$500, B10, $J$6:$J$500)) -> 79.8 | P10: =IF(OR(ISBLANK(M10),ISBLANK(N10),N10=0), "", M10/N10) -> 0
B11: =IF(AND(ISBLANK(D11), ISBLANK(E11), ISBLANK(G11)), "", IF(AND(E11<>"", E11=E10, D11<>"", D11=D10), B10, "PED-" & TEXT(IFERROR(VALUE(RIGHT(LOOKUP("PED-9999",$B$5:B10),4)),1000)+1, "0000"))) -> PED-1006 | C11: V-006 | D11: 46300 | E11: LUCIA HELENA | F11: =IF(ISBLANK(E11),"",IFERROR(VLOOKUP(E11,'CADASTRO DE CLIENTES'!$C$6:$E$500,3,FALSE),"")) -> 18 98205-2963 | G11: MANTA SOFT CASAL SIMPLES | H11: 2 | I11: =IF(ISBLANK(G11),"",IFERROR(VLOOKUP(G11,'CADASTRO DE MATERIAL'!$C$6:$J$500,8,FALSE),"")) -> 39.9 | J11: =IF(OR(ISBLANK(H11),ISBLANK(I11)), "", H11*I11) -> 79.8 | K11: A Prazo | L11: =IF(ISBLANK(B11), "", IF(K11="À Vista", O11, 0)) -> 0 | M11: =IF(ISBLANK(B11),"", O11 - IF(ISBLANK(L11), 0, L11)) -> 79.8 | N11: 1 | O11: =IF(ISBLANK(B11),"", SUMIF($B$6:$B$500, B11, $J$6:$J$500)) -> 79.8 | P11: =IF(OR(ISBLANK(M11),ISBLANK(N11),N11=0), "", M11/N11) -> 79.8
B12: =IF(AND(ISBLANK(D12), ISBLANK(E12), ISBLANK(G12)), "", IF(AND(E12<>"", E12=E11, D12<>"", D12=D11), B11, "PED-" & TEXT(IFERROR(VALUE(RIGHT(LOOKUP("PED-9999",$B$5:B11),4)),1000)+1, "0000"))) -> PED-1007 | C12: V-007 | D12: 46300 | E12: CLAUDIA SILVA | F12: =IF(ISBLANK(E12),"",IFERROR(VLOOKUP(E12,'CADASTRO DE CLIENTES'!$C$6:$E$500,3,FALSE),"")) -> 0 | G12: PASSADEIRA SEDA 2 | H12: 1 | I12: =IF(ISBLANK(G12),"",IFERROR(VLOOKUP(G12,'CADASTRO DE MATERIAL'!$C$6:$J$500,8,FALSE),"")) -> 239.9 | J12: =IF(OR(ISBLANK(H12),ISBLANK(I12)), "", H12*I12) -> 239.9 | K12: A Prazo | L12: =IF(ISBLANK(B12), "", IF(K12="À Vista", O12, 0)) -> 0 | M12: =IF(ISBLANK(B12),"", O12 - IF(ISBLANK(L12), 0, L12)) -> 239.9 | N12: 1 | O12: =IF(ISBLANK(B12),"", SUMIF($B$6:$B$500, B12, $J$6:$J$500)) -> 239.9 | P12: =IF(OR(ISBLANK(M12),ISBLANK(N12),N12=0), "", M12/N12) -> 239.9
B13: =IF(AND(ISBLANK(D13), ISBLANK(E13), ISBLANK(G13)), "", IF(AND(E13<>"", E13=E12, D13<>"", D13=D12), B12, "PED-" & TEXT(IFERROR(VALUE(RIGHT(LOOKUP("PED-9999",$B$5:B12),4)),1000)+1, "0000"))) -> PED-1008 | C13: V-008 | D13: 46301 | E13: SONIA MARIA | F13: =IF(ISBLANK(E13),"",IFERROR(VLOOKUP(E13,'CADASTRO DE CLIENTES'!$C$6:$E$500,3,FALSE),"")) -> 0 | G13: TOALHA DE CHA 90X90 | H13: 1 | I13: =IF(ISBLANK(G13),"",IFERROR(VLOOKUP(G13,'CADASTRO DE MATERIAL'!$C$6:$J$500,8,FALSE),"")) -> 39.9 | J13: =IF(OR(ISBLANK(H13),ISBLANK(I13)), "", H13*I13) -> 39.9 | K13: A Prazo | L13: =IF(ISBLANK(B13), "", IF(K13="À Vista", O13, 0)) -> 0 | M13: =IF(ISBLANK(B13),"", O13 - IF(ISBLANK(L13), 0, L13)) -> 39.9 | N13: 1 | O13: =IF(ISBLANK(B13),"", SUMIF($B$6:$B$500, B13, $J$6:$J$500)) -> 39.9 | P13: =IF(OR(ISBLANK(M13),ISBLANK(N13),N13=0), "", M13/N13) -> 39.9
B14: =IF(AND(ISBLANK(D14), ISBLANK(E14), ISBLANK(G14)), "", IF(AND(E14<>"", E14=E13, D14<>"", D14=D13), B13, "PED-" & TEXT(IFERROR(VALUE(RIGHT(LOOKUP("PED-9999",$B$5:B13),4)),1000)+1, "0000"))) -> PED-1009 | C14: V-009 | D14: 46301 | E14: ROSE GALDINO | F14: =IF(ISBLANK(E14),"",IFERROR(VLOOKUP(E14,'CADASTRO DE CLIENTES'!$C$6:$E$500,3,FALSE),"")) -> 0 | G14: MANTA SOFT CASAL SIMPLES | H14: 1 | I14: =IF(ISBLANK(G14),"",IFERROR(VLOOKUP(G14,'CADASTRO DE MATERIAL'!$C$6:$J$500,8,FALSE),"")) -> 39.9 | J14: =IF(OR(ISBLANK(H14),ISBLANK(I14)), "", H14*I14) -> 39.9 | K14: A Prazo | L14: =IF(ISBLANK(B14), "", IF(K14="À Vista", O14, 0)) -> 0 | M14: =IF(ISBLANK(B14),"", O14 - IF(ISBLANK(L14), 0, L14)) -> 39.9 | N14: 1 | O14: =IF(ISBLANK(B14),"", SUMIF($B$6:$B$500, B14, $J$6:$J$500)) -> 39.9 | P14: =IF(OR(ISBLANK(M14),ISBLANK(N14),N14=0), "", M14/N14) -> 39.9
B15: =IF(AND(ISBLANK(D15), ISBLANK(E15), ISBLANK(G15)), "", IF(AND(E15<>"", E15=E14, D15<>"", D15=D14), B14, "PED-" & TEXT(IFERROR(VALUE(RIGHT(LOOKUP("PED-9999",$B$5:B14),4)),1000)+1, "0000"))) -> PED-1010 | C15: V-010 | D15: 46302 | E15: ADRIANA PEDRO | F15: =IF(ISBLANK(E15),"",IFERROR(VLOOKUP(E15,'CADASTRO DE CLIENTES'!$C$6:$E$500,3,FALSE),"")) -> 18 99818-0064 | G15: KIT LENÇOL KING 5200 FIOS 3 PEÇAS | H15: 1 | I15: =IF(ISBLANK(G15),"",IFERROR(VLOOKUP(G15,'CADASTRO DE MATERIAL'!$C$6:$J$500,8,FALSE),"")) -> 159.9 | J15: =IF(OR(ISBLANK(H15),ISBLANK(I15)), "", H15*I15) -> 159.9 | K15: A Prazo | L15: =IF(ISBLANK(B15), "", IF(K15="À Vista", O15, 0)) -> 0 | M15: =IF(ISBLANK(B15),"", O15 - IF(ISBLANK(L15), 0, L15)) -> 159.9 | N15: 1 | O15: =IF(ISBLANK(B15),"", SUMIF($B$6:$B$500, B15, $J$6:$J$500)) -> 159.9 | P15: =IF(OR(ISBLANK(M15),ISBLANK(N15),N15=0), "", M15/N15) -> 159.9
B16: =IF(AND(ISBLANK(D16), ISBLANK(E16), ISBLANK(G16)), "", IF(AND(E16<>"", E16=E15, D16<>"", D16=D15), B15, "PED-" & TEXT(IFERROR(VALUE(RIGHT(LOOKUP("PED-9999",$B$5:B15),4)),1000)+1, "0000"))) -> PED-1011 | C16: V-011 | D16: 46302 | E16: SONIA MARIA | F16: =IF(ISBLANK(E16),"",IFERROR(VLOOKUP(E16,'CADASTRO DE CLIENTES'!$C$6:$E$500,3,FALSE),"")) -> 0 | G16: JOGO DE PASSADEIRA MALHA 3 PEÇAS 1,50 | H16: 1 | I16: =IF(ISBLANK(G16),"",IFERROR(VLOOKUP(G16,'CADASTRO DE MATERIAL'!$C$6:$J$500,8,FALSE),"")) -> 99.9 | J16: =IF(OR(ISBLANK(H16),ISBLANK(I16)), "", H16*I16) -> 99.9 | K16: A Prazo | L16: =IF(ISBLANK(B16), "", IF(K16="À Vista", O16, 0)) -> 0 | M16: =IF(ISBLANK(B16),"", O16 - IF(ISBLANK(L16), 0, L16)) -> 99.9 | N16: 1 | O16: =IF(ISBLANK(B16),"", SUMIF($B$6:$B$500, B16, $J$6:$J$500)) -> 99.9 | P16: =IF(OR(ISBLANK(M16),ISBLANK(N16),N16=0), "", M16/N16) -> 99.9
B17: =IF(AND(ISBLANK(D17), ISBLANK(E17), ISBLANK(G17)), "", IF(AND(E17<>"", E17=E16, D17<>"", D17=D16), B16, "PED-" & TEXT(IFERROR(VALUE(RIGHT(LOOKUP("PED-9999",$B$5:B16),4)),1000)+1, "0000"))) -> PED-1012 | C17: V-012 | D17: 46302 | E17: HADIJA | F17: =IF(ISBLANK(E17),"",IFERROR(VLOOKUP(E17,'CADASTRO DE CLIENTES'!$C$6:$E$500,3,FALSE),"")) -> 0 | G17: MANTA QUEEN ALGODAO 2,20X2,50 | H17: 1 | I17: =IF(ISBLANK(G17),"",IFERROR(VLOOKUP(G17,'CADASTRO DE MATERIAL'!$C$6:$J$500,8,FALSE),"")) -> 119.9 | J17: =IF(OR(ISBLANK(H17),ISBLANK(I17)), "", H17*I17) -> 119.9 | K17: A Prazo | L17: 0 | M17: =IF(ISBLANK(B17),"", O17 - IF(ISBLANK(L17), 0, L17)) -> 501.4 | N17: 3 | O17: =IF(ISBLANK(B17),"", SUMIF($B$6:$B$500, B17, $J$6:$J$500)) -> 501.4 | P17: =IF(OR(ISBLANK(M17),ISBLANK(N17),N17=0), "", M17/N17) -> 167.13333
B18: =IF(AND(ISBLANK(D18), ISBLANK(E18), ISBLANK(G18)), "", IF(AND(E18<>"", E18=E17, D18<>"", D18=D17), B17, "PED-" & TEXT(IFERROR(VALUE(RIGHT(LOOKUP("PED-9999",$B$5:B17),4)),1000)+1, "0000"))) -> PED-1012 | C18: V-013 | D18: 46302 | E18: HADIJA | F18: =IF(ISBLANK(E18),"",IFERROR(VLOOKUP(E18,'CADASTRO DE CLIENTES'!$C$6:$E$500,3,FALSE),"")) -> 0 | G18: JOGO DE PASSADEIRA MALHA 3 PEÇAS 1,50 | H18: 1 | I18: =IF(ISBLANK(G18),"",IFERROR(VLOOKUP(G18,'CADASTRO DE MATERIAL'!$C$6:$J$500,8,FALSE),"")) -> 99.9 | J18: =IF(OR(ISBLANK(H18),ISBLANK(I18)), "", H18*I18) -> 99.9 | K18: A Prazo | L18: =IF(ISBLANK(B18), "", IF(K18="À Vista", O18, 0)) -> 0 | M18: =IF(ISBLANK(B18),"", O18 - IF(ISBLANK(L18), 0, L18)) -> 501.4 | N18: 3 | O18: =IF(ISBLANK(B18),"", SUMIF($B$6:$B$500, B18, $J$6:$J$500)) -> 501.4 | P18: =IF(OR(ISBLANK(M18),ISBLANK(N18),N18=0), "", M18/N18) -> 167.13333
B19: =IF(AND(ISBLANK(D19), ISBLANK(E19), ISBLANK(G19)), "", IF(AND(E19<>"", E19=E18, D19<>"", D19=D18), B18, "PED-" & TEXT(IFERROR(VALUE(RIGHT(LOOKUP("PED-9999",$B$5:B18),4)),1000)+1, "0000"))) -> PED-1012 | C19: V-014 | D19: 46302 | E19: HADIJA | F19: =IF(ISBLANK(E19),"",IFERROR(VLOOKUP(E19,'CADASTRO DE CLIENTES'!$C$6:$E$500,3,FALSE),"")) -> 0 | G19: PAR TAPETE MALHA 50X80 | H19: 1 | I19: =IF(ISBLANK(G19),"",IFERROR(VLOOKUP(G19,'CADASTRO DE MATERIAL'!$C$6:$J$500,8,FALSE),"")) -> 49.9 | J19: =IF(OR(ISBLANK(H19),ISBLANK(I19)), "", H19*I19) -> 49.9 | K19: A Prazo | L19: =IF(ISBLANK(B19), "", IF(K19="À Vista", O19, 0)) -> 0 | M19: =IF(ISBLANK(B19),"", O19 - IF(ISBLANK(L19), 0, L19)) -> 501.4 | N19: 3 | O19: =IF(ISBLANK(B19),"", SUMIF($B$6:$B$500, B19, $J$6:$J$500)) -> 501.4 | P19: =IF(OR(ISBLANK(M19),ISBLANK(N19),N19=0), "", M19/N19) -> 167.13333
B20: =IF(AND(ISBLANK(D20), ISBLANK(E20), ISBLANK(G20)), "", IF(AND(E20<>"", E20=E19, D20<>"", D20=D19), B19, "PED-" & TEXT(IFERROR(VALUE(RIGHT(LOOKUP("PED-9999",$B$5:B19),4)),1000)+1, "0000"))) -> PED-1012 | C20: V-015 | D20: 46302 | E20: HADIJA | F20: =IF(ISBLANK(E20),"",IFERROR(VLOOKUP(E20,'CADASTRO DE CLIENTES'!$C$6:$E$500,3,FALSE),"")) -> 0 | G20: PAR PASSADEIRA LUXO 50X1,50 | H20: 1 | I20: =IF(ISBLANK(G20),"",IFERROR(VLOOKUP(G20,'CADASTRO DE MATERIAL'!$C$6:$J$500,8,FALSE),"")) -> 139.9 | J20: =IF(OR(ISBLANK(H20),ISBLANK(I20)), "", H20*I20) -> 139.9 | K20: A Prazo | L20: =IF(ISBLANK(B20), "", IF(K20="À Vista", O20, 0)) -> 0 | M20: =IF(ISBLANK(B20),"", O20 - IF(ISBLANK(L20), 0, L20)) -> 501.4 | N20: 3 | O20: =IF(ISBLANK(B20),"", SUMIF($B$6:$B$500, B20, $J$6:$J$500)) -> 501.4 | P20: =IF(OR(ISBLANK(M20),ISBLANK(N20),N20=0), "", M20/N20) -> 167.13333
B21: =IF(AND(ISBLANK(D21), ISBLANK(E21), ISBLANK(G21)), "", IF(AND(E21<>"", E21=E20, D21<>"", D21=D20), B20, "PED-" & TEXT(IFERROR(VALUE(RIGHT(LOOKUP("PED-9999",$B$5:B20),4)),1000)+1, "0000"))) -> PED-1012 | C21: V-016 | D21: 46302 | E21: HADIJA | F21: =IF(ISBLANK(E21),"",IFERROR(VLOOKUP(E21,'CADASTRO DE CLIENTES'!$C$6:$E$500,3,FALSE),"")) -> 0 | G21: TAPETE PREMIUM 50X80 | H21: 2 | I21: =IF(ISBLANK(G21),"",IFERROR(VLOOKUP(G21,'CADASTRO DE MATERIAL'!$C$6:$J$500,8,FALSE),"")) -> 45.9 | J21: =IF(OR(ISBLANK(H21),ISBLANK(I21)), "", H21*I21) -> 91.8 | K21: A Prazo | L21: =IF(ISBLANK(B21), "", IF(K21="À Vista", O21, 0)) -> 0 | M21: =IF(ISBLANK(B21),"", O21 - IF(ISBLANK(L21), 0, L21)) -> 501.4 | N21: 3 | O21: =IF(ISBLANK(B21),"", SUMIF($B$6:$B$500, B21, $J$6:$J$500)) -> 501.4 | P21: =IF(OR(ISBLANK(M21),ISBLANK(N21),N21=0), "", M21/N21) -> 167.13333
B22: =IF(AND(ISBLANK(D22), ISBLANK(E22), ISBLANK(G22)), "", IF(AND(E22<>"", E22=E21, D22<>"", D22=D21), B21, "PED-" & TEXT(IFERROR(VALUE(RIGHT(LOOKUP("PED-9999",$B$5:B21),4)),1000)+1, "0000"))) -> PED-1013 | C22: V-017 | D22: 46303 | E22: JULIANA CORREA | F22: =IF(ISBLANK(E22),"",IFERROR(VLOOKUP(E22,'CADASTRO DE CLIENTES'!$C$6:$E$500,3,FALSE),"")) -> 0 | G22: TAPETE CIZAL PORTA 40X60 | H22: 2 | I22: =IF(ISBLANK(G22),"",IFERROR(VLOOKUP(G22,'CADASTRO DE MATERIAL'!$C$6:$J$500,8,FALSE),"")) -> 69.9 | J22: =IF(OR(ISBLANK(H22),ISBLANK(I22)), "", H22*I22) -> 139.8 | K22: A Prazo | L22: =IF(ISBLANK(B22), "", IF(K22="À Vista", O22, 0)) -> 0 | M22: =IF(ISBLANK(B22),"", O22 - IF(ISBLANK(L22), 0, L22)) -> 139.8 | N22: 1 | O22: =IF(ISBLANK(B22),"", SUMIF($B$6:$B$500, B22, $J$6:$J$500)) -> 139.8 | P22: =IF(OR(ISBLANK(M22),ISBLANK(N22),N22=0), "", M22/N22) -> 139.8
B23: =IF(AND(ISBLANK(D23), ISBLANK(E23), ISBLANK(G23)), "", IF(AND(E23<>"", E23=E22, D23<>"", D23=D22), B22, "PED-" & TEXT(IFERROR(VALUE(RIGHT(LOOKUP("PED-9999",$B$5:B22),4)),1000)+1, "0000"))) -> PED-1014 | C23: V-018 | D23: 46303 | E23: DEIGILAN | F23: =IF(ISBLANK(E23),"",IFERROR(VLOOKUP(E23,'CADASTRO DE CLIENTES'!$C$6:$E$500,3,FALSE),"")) -> 0 | G23: PAR TAPETE MALHA 50X80 | H23: 1 | I23: =IF(ISBLANK(G23),"",IFERROR(VLOOKUP(G23,'CADASTRO DE MATERIAL'!$C$6:$J$500,8,FALSE),"")) -> 49.9 | J23: =IF(OR(ISBLANK(H23),ISBLANK(I23)), "", H23*I23) -> 49.9 | K23: A Prazo | L23: =IF(ISBLANK(B23), "", IF(K23="À Vista", O23, 0)) -> 0 | M23: =IF(ISBLANK(B23),"", O23 - IF(ISBLANK(L23), 0, L23)) -> 49.9 | N23: 1 | O23: =IF(ISBLANK(B23),"", SUMIF($B$6:$B$500, B23, $J$6:$J$500)) -> 49.9 | P23: =IF(OR(ISBLANK(M23),ISBLANK(N23),N23=0), "", M23/N23) -> 49.9
B24: =IF(AND(ISBLANK(D24), ISBLANK(E24), ISBLANK(G24)), "", IF(AND(E24<>"", E24=E23, D24<>"", D24=D23), B23, "PED-" & TEXT(IFERROR(VALUE(RIGHT(LOOKUP("PED-9999",$B$5:B23),4)),1000)+1, "0000"))) -> PED-1015 | C24: V-019 | D24: 46303 | E24: ANDREIA FERREIRA | F24: =IF(ISBLANK(E24),"",IFERROR(VLOOKUP(E24,'CADASTRO DE CLIENTES'!$C$6:$E$500,3,FALSE),"")) -> 0 | G24: TAPETE CIZAL PORTA 40X60 | H24: 1 | I24: =IF(ISBLANK(G24),"",IFERROR(VLOOKUP(G24,'CADASTRO DE MATERIAL'!$C$6:$J$500,8,FALSE),"")) -> 69.9 | J24: =IF(OR(ISBLANK(H24),ISBLANK(I24)), "", H24*I24) -> 69.9 | K24: À Vista | L24: =IF(ISBLANK(B24), "", IF(K24="À Vista", O24, 0)) -> 69.9 | M24: =IF(ISBLANK(B24),"", O24 - IF(ISBLANK(L24), 0, L24)) -> 0 | N24: 1 | O24: =IF(ISBLANK(B24),"", SUMIF($B$6:$B$500, B24, $J$6:$J$500)) -> 69.9 | P24: =IF(OR(ISBLANK(M24),ISBLANK(N24),N24=0), "", M24/N24) -> 0
B25: =IF(AND(ISBLANK(D25), ISBLANK(E25), ISBLANK(G25)), "", IF(AND(E25<>"", E25=E24, D25<>"", D25=D24), B24, "PED-" & TEXT(IFERROR(VALUE(RIGHT(LOOKUP("PED-9999",$B$5:B24),4)),1000)+1, "0000"))) -> PED-1016 | C25: V-020 | D25: 46303 | E25: CLEIDE LOPES | F25: =IF(ISBLANK(E25),"",IFERROR(VLOOKUP(E25,'CADASTRO DE CLIENTES'!$C$6:$E$500,3,FALSE),"")) -> 0 | G25: TAPETE AQUARELA 50X80 | H25: 1 | I25: =IF(ISBLANK(G25),"",IFERROR(VLOOKUP(G25,'CADASTRO DE MATERIAL'!$C$6:$J$500,8,FALSE),"")) -> 39.9 | J25: =IF(OR(ISBLANK(H25),ISBLANK(I25)), "", H25*I25) -> 39.9 | K25: À Vista | L25: =IF(ISBLANK(B25), "", IF(K25="À Vista", O25, 0)) -> 39.9 | M25: =IF(ISBLANK(B25),"", O25 - IF(ISBLANK(L25), 0, L25)) -> 0 | N25: 1 | O25: =IF(ISBLANK(B25),"", SUMIF($B$6:$B$500, B25, $J$6:$J$500)) -> 39.9 | P25: =IF(OR(ISBLANK(M25),ISBLANK(N25),N25=0), "", M25/N25) -> 0
B26: =IF(AND(ISBLANK(D26), ISBLANK(E26), ISBLANK(G26)), "", IF(AND(E26<>"", E26=E25, D26<>"", D26=D25), B25, "PED-" & TEXT(IFERROR(VALUE(RIGHT(LOOKUP("PED-9999",$B$5:B25),4)),1000)+1, "0000"))) -> PED-1017 | C26: V-021 | D26: 46303 | E26: DEIGILAN | F26: =IF(ISBLANK(E26),"",IFERROR(VLOOKUP(E26,'CADASTRO DE CLIENTES'!$C$6:$E$500,3,FALSE),"")) -> 0 | G26: CAMINHO DE MESA NATAL 1,0 | H26: 1 | I26: =IF(ISBLANK(G26),"",IFERROR(VLOOKUP(G26,'CADASTRO DE MATERIAL'!$C$6:$J$500,8,FALSE),"")) -> 49.9 | J26: =IF(OR(ISBLANK(H26),ISBLANK(I26)), "", H26*I26) -> 49.9 | K26: A Prazo | L26: =IF(ISBLANK(B26), "", IF(K26="À Vista", O26, 0)) -> 0 | M26: =IF(ISBLANK(B26),"", O26 - IF(ISBLANK(L26), 0, L26)) -> 49.9 | N26: 1 | O26: =IF(ISBLANK(B26),"", SUMIF($B$6:$B$500, B26, $J$6:$J$500)) -> 49.9 | P26: =IF(OR(ISBLANK(M26),ISBLANK(N26),N26=0), "", M26/N26) -> 49.9
B27: =IF(AND(ISBLANK(D27), ISBLANK(E27), ISBLANK(G27)), "", IF(AND(E27<>"", E27=E26, D27<>"", D27=D26), B26, "PED-" & TEXT(IFERROR(VALUE(RIGHT(LOOKUP("PED-9999",$B$5:B26),4)),1000)+1, "0000"))) -> PED-1018 | C27: V-022 | D27: 46303 | E27: MADALENA UNIMED | F27: =IF(ISBLANK(E27),"",IFERROR(VLOOKUP(E27,'CADASTRO DE CLIENTES'!$C$6:$E$500,3,FALSE),"")) -> 0 | G27: TAPETE CIZAL PORTA 40X60 | H27: 1 | I27: =IF(ISBLANK(G27),"",IFERROR(VLOOKUP(G27,'CADASTRO DE MATERIAL'!$C$6:$J$500,8,FALSE),"")) -> 69.9 | J27: =IF(OR(ISBLANK(H27),ISBLANK(I27)), "", H27*I27) -> 69.9 | K27: À Vista | L27: =IF(ISBLANK(B27), "", IF(K27="À Vista", O27, 0)) -> 69.9 | M27: =IF(ISBLANK(B27),"", O27 - IF(ISBLANK(L27), 0, L27)) -> 0 | N27: 1 | O27: =IF(ISBLANK(B27),"", SUMIF($B$6:$B$500, B27, $J$6:$J$500)) -> 69.9 | P27: =IF(OR(ISBLANK(M27),ISBLANK(N27),N27=0), "", M27/N27) -> 0
B28: =IF(AND(ISBLANK(D28), ISBLANK(E28), ISBLANK(G28)), "", IF(AND(E28<>"", E28=E27, D28<>"", D28=D27), B27, "PED-" & TEXT(IFERROR(VALUE(RIGHT(LOOKUP("PED-9999",$B$5:B27),4)),1000)+1, "0000"))) -> PED-1019 | C28: V-023 | D28: 46303 | E28: SONIA MARIA | F28: =IF(ISBLANK(E28),"",IFERROR(VLOOKUP(E28,'CADASTRO DE CLIENTES'!$C$6:$E$500,3,FALSE),"")) -> 0 | G28: TAPETE CIZAL PORTA 40X60 | H28: 1 | I28: =IF(ISBLANK(G28),"",IFERROR(VLOOKUP(G28,'CADASTRO DE MATERIAL'!$C$6:$J$500,8,FALSE),"")) -> 69.9 | J28: =IF(OR(ISBLANK(H28),ISBLANK(I28)), "", H28*I28) -> 69.9 | K28: A Prazo | L28: =IF(ISBLANK(B28), "", IF(K28="À Vista", O28, 0)) -> 0 | M28: =IF(ISBLANK(B28),"", O28 - IF(ISBLANK(L28), 0, L28)) -> 69.9 | N28: 1 | O28: =IF(ISBLANK(B28),"", SUMIF($B$6:$B$500, B28, $J$6:$J$500)) -> 69.9 | P28: =IF(OR(ISBLANK(M28),ISBLANK(N28),N28=0), "", M28/N28) -> 69.9
B29: =IF(AND(ISBLANK(D29), ISBLANK(E29), ISBLANK(G29)), "", IF(AND(E29<>"", E29=E28, D29<>"", D29=D28), B28, "PED-" & TEXT(IFERROR(VALUE(RIGHT(LOOKUP("PED-9999",$B$5:B28),4)),1000)+1, "0000"))) -> PED-1020 | C29: V-024 | D29: 46303 | E29: EDINA REGINA | F29: =IF(ISBLANK(E29),"",IFERROR(VLOOKUP(E29,'CADASTRO DE CLIENTES'!$C$6:$E$500,3,FALSE),"")) -> 0 | G29: TAPETE DUPLA FACE TRADIOCIONAL CAFÉ CARAMELO | H29: 1 | I29: =IF(ISBLANK(G29),"",IFERROR(VLOOKUP(G29,'CADASTRO DE MATERIAL'!$C$6:$J$500,8,FALSE),"")) -> 39.9 | J29: =IF(OR(ISBLANK(H29),ISBLANK(I29)), "", H29*I29) -> 39.9 | K29: A Prazo | L29: =IF(ISBLANK(B29), "", IF(K29="À Vista", O29, 0)) -> 0 | M29: =IF(ISBLANK(B29),"", O29 - IF(ISBLANK(L29), 0, L29)) -> 39.9 | N29: 1 | O29: =IF(ISBLANK(B29),"", SUMIF($B$6:$B$500, B29, $J$6:$J$500)) -> 39.9 | P29: =IF(OR(ISBLANK(M29),ISBLANK(N29),N29=0), "", M29/N29) -> 39.9
... B32: =IF(AND(ISBLANK(D32), ISBLANK(E32), ISBLANK(G32)), "", IF(AND(E32<>"", E32=E31, D32<>"", D32=D31), B31, "PED-" & TEXT(IFERROR(VALUE(RIGHT(LOOKUP("PED-9999",$B$5:B31),4)),1000)+1, "0000"))) -> PED-1023 | C32: V-027 | D32: 46304 | E32: ROSE GALDINO | F32: =IF(ISBLANK(E32),"",IFERROR(VLOOKUP(E32,'CADASTRO DE CLIENTES'!$C$6:$E$500,3,FALSE),"")) -> 0 | G32: JOGO PASSADEIRA 3 PEÇAS 2,0 | H32: 1 | I32: =IF(ISBLANK(G32),"",IFERROR(VLOOKUP(G32,'CADASTRO DE MATERIAL'!$C$6:$J$500,8,FALSE),"")) -> 129.9 | J32: =IF(OR(ISBLANK(H32),ISBLANK(I32)), "", H32*I32) -> 129.9 | K32: A Prazo | L32: =IF(ISBLANK(B32), "", IF(K32="À Vista", O32, 0)) -> 0 | M32: =IF(ISBLANK(B32),"", O32 - IF(ISBLANK(L32), 0, L32)) -> 129.9 | N32: 1 | O32: =IF(ISBLANK(B32),"", SUMIF($B$6:$B$500, B32, $J$6:$J$500)) -> 129.9 | P32: =IF(OR(ISBLANK(M32),ISBLANK(N32),N32=0), "", M32/N32) -> 129.9
B33: =IF(AND(ISBLANK(D33), ISBLANK(E33), ISBLANK(G33)), "", IF(AND(E33<>"", E33=E32, D33<>"", D33=D32), B32, "PED-" & TEXT(IFERROR(VALUE(RIGHT(LOOKUP("PED-9999",$B$5:B32),4)),1000)+1, "0000"))) | C33: V-028 | F33: =IF(ISBLANK(E33),"",IFERROR(VLOOKUP(E33,'CADASTRO DE CLIENTES'!$C$6:$E$500,3,FALSE),"")) | I33: =IF(ISBLANK(G33),"",IFERROR(VLOOKUP(G33,'CADASTRO DE MATERIAL'!$C$6:$J$500,8,FALSE),"")) | J33: =IF(OR(ISBLANK(H33),ISBLANK(I33)), "", H33*I33) | L33: =IF(ISBLANK(B33), "", IF(K33="À Vista", O33, 0)) -> 0 | M33: =IF(ISBLANK(B33),"", O33 - IF(ISBLANK(L33), 0, L33)) -> 0 | O33: =IF(ISBLANK(B33),"", SUMIF($B$6:$B$500, B33, $J$6:$J$500)) -> 0 | P33: =IF(OR(ISBLANK(M33),ISBLANK(N33),N33=0), "", M33/N33)
B34: =IF(AND(ISBLANK(D34), ISBLANK(E34), ISBLANK(G34)), "", IF(AND(E34<>"", E34=E33, D34<>"", D34=D33), B33, "PED-" & TEXT(IFERROR(VALUE(RIGHT(LOOKUP("PED-9999",$B$5:B33),4)),1000)+1, "0000"))) | C34: V-029 | F34: =IF(ISBLANK(E34),"",IFERROR(VLOOKUP(E34,'CADASTRO DE CLIENTES'!$C$6:$E$500,3,FALSE),"")) | I34: =IF(ISBLANK(G34),"",IFERROR(VLOOKUP(G34,'CADASTRO DE MATERIAL'!$C$6:$J$500,8,FALSE),"")) | J34: =IF(OR(ISBLANK(H34),ISBLANK(I34)), "", H34*I34) | L34: =IF(ISBLANK(B34), "", IF(K34="À Vista", O34, 0)) -> 0 | M34: =IF(ISBLANK(B34),"", O34 - IF(ISBLANK(L34), 0, L34)) -> 0 | O34: =IF(ISBLANK(B34),"", SUMIF($B$6:$B$500, B34, $J$6:$J$500)) -> 0 | P34: =IF(OR(ISBLANK(M34),ISBLANK(N34),N34=0), "", M34/N34)
B35: =IF(AND(ISBLANK(D35), ISBLANK(E35), ISBLANK(G35)), "", IF(AND(E35<>"", E35=E34, D35<>"", D35=D34), B34, "PED-" & TEXT(IFERROR(VALUE(RIGHT(LOOKUP("PED-9999",$B$5:B34),4)),1000)+1, "0000"))) | C35: V-030 | F35: =IF(ISBLANK(E35),"",IFERROR(VLOOKUP(E35,'CADASTRO DE CLIENTES'!$C$6:$E$500,3,FALSE),"")) | I35: =IF(ISBLANK(G35),"",IFERROR(VLOOKUP(G35,'CADASTRO DE MATERIAL'!$C$6:$J$500,8,FALSE),"")) | J35: =IF(OR(ISBLANK(H35),ISBLANK(I35)), "", H35*I35) | L35: =IF(ISBLANK(B35), "", IF(K35="À Vista", O35, 0)) -> 0 | M35: =IF(ISBLANK(B35),"", O35 - IF(ISBLANK(L35), 0, L35)) -> 0 | O35: =IF(ISBLANK(B35),"", SUMIF($B$6:$B$500, B35, $J$6:$J$500)) -> 0 | P35: =IF(OR(ISBLANK(M35),ISBLANK(N35),N35=0), "", M35/N35)
B36: =IF(AND(ISBLANK(D36), ISBLANK(E36), ISBLANK(G36)), "", IF(AND(E36<>"", E36=E35, D36<>"", D36=D35), B35, "PED-" & TEXT(IFERROR(VALUE(RIGHT(LOOKUP("PED-9999",$B$5:B35),4)),1000)+1, "0000"))) | C36: V-031 | F36: =IF(ISBLANK(E36),"",IFERROR(VLOOKUP(E36,'CADASTRO DE CLIENTES'!$C$6:$E$500,3,FALSE),"")) | I36: =IF(ISBLANK(G36),"",IFERROR(VLOOKUP(G36,'CADASTRO DE MATERIAL'!$C$6:$J$500,8,FALSE),"")) | J36: =IF(OR(ISBLANK(H36),ISBLANK(I36)), "", H36*I36) | L36: =IF(ISBLANK(B36), "", IF(K36="À Vista", O36, 0)) -> 0 | M36: =IF(ISBLANK(B36),"", O36 - IF(ISBLANK(L36), 0, L36)) -> 0 | O36: =IF(ISBLANK(B36),"", SUMIF($B$6:$B$500, B36, $J$6:$J$500)) -> 0 | P36: =IF(OR(ISBLANK(M36),ISBLANK(N36),N36=0), "", M36/N36)
B37: =IF(AND(ISBLANK(D37), ISBLANK(E37), ISBLANK(G37)), "", IF(AND(E37<>"", E37=E36, D37<>"", D37=D36), B36, "PED-" & TEXT(IFERROR(VALUE(RIGHT(LOOKUP("PED-9999",$B$5:B36),4)),1000)+1, "0000"))) | C37: V-032 | F37: =IF(ISBLANK(E37),"",IFERROR(VLOOKUP(E37,'CADASTRO DE CLIENTES'!$C$6:$E$500,3,FALSE),"")) | I37: =IF(ISBLANK(G37),"",IFERROR(VLOOKUP(G37,'CADASTRO DE MATERIAL'!$C$6:$J$500,8,FALSE),"")) | J37: =IF(OR(ISBLANK(H37),ISBLANK(I37)), "", H37*I37) | L37: =IF(ISBLANK(B37), "", IF(K37="À Vista", O37, 0)) -> 0 | M37: =IF(ISBLANK(B37),"", O37 - IF(ISBLANK(L37), 0, L37)) -> 0 | O37: =IF(ISBLANK(B37),"", SUMIF($B$6:$B$500, B37, $J$6:$J$500)) -> 0 | P37: =IF(OR(ISBLANK(M37),ISBLANK(N37),N37=0), "", M37/N37)
B38: =IF(AND(ISBLANK(D38), ISBLANK(E38), ISBLANK(G38)), "", IF(AND(E38<>"", E38=E37, D38<>"", D38=D37), B37, "PED-" & TEXT(IFERROR(VALUE(RIGHT(LOOKUP("PED-9999",$B$5:B37),4)),1000)+1, "0000"))) | C38: V-033 | F38: =IF(ISBLANK(E38),"",IFERROR(VLOOKUP(E38,'CADASTRO DE CLIENTES'!$C$6:$E$500,3,FALSE),"")) | I38: =IF(ISBLANK(G38),"",IFERROR(VLOOKUP(G38,'CADASTRO DE MATERIAL'!$C$6:$J$500,8,FALSE),"")) | J38: =IF(OR(ISBLANK(H38),ISBLANK(I38)), "", H38*I38) | L38: =IF(ISBLANK(B38), "", IF(K38="À Vista", O38, 0)) -> 0 | M38: =IF(ISBLANK(B38),"", O38 - IF(ISBLANK(L38), 0, L38)) -> 0 | O38: =IF(ISBLANK(B38),"", SUMIF($B$6:$B$500, B38, $J$6:$J$500)) -> 0 | P38: =IF(OR(ISBLANK(M38),ISBLANK(N38),N38=0), "", M38/N38)
B39: =IF(AND(ISBLANK(D39), ISBLANK(E39), ISBLANK(G39)), "", IF(AND(E39<>"", E39=E38, D39<>"", D39=D38), B38, "PED-" & TEXT(IFERROR(VALUE(RIGHT(LOOKUP("PED-9999",$B$5:B38),4)),1000)+1, "0000"))) | C39: V-034 | F39: =IF(ISBLANK(E39),"",IFERROR(VLOOKUP(E39,'CADASTRO DE CLIENTES'!$C$6:$E$500,3,FALSE),"")) | I39: =IF(ISBLANK(G39),"",IFERROR(VLOOKUP(G39,'CADASTRO DE MATERIAL'!$C$6:$J$500,8,FALSE),"")) | J39: =IF(OR(ISBLANK(H39),ISBLANK(I39)), "", H39*I39) | L39: =IF(ISBLANK(B39), "", IF(K39="À Vista", O39, 0)) -> 0 | M39: =IF(ISBLANK(B39),"", O39 - IF(ISBLANK(L39), 0, L39)) -> 0 | O39: =IF(ISBLANK(B39),"", SUMIF($B$6:$B$500, B39, $J$6:$J$500)) -> 0 | P39: =IF(OR(ISBLANK(M39),ISBLANK(N39),N39=0), "", M39/N39)
B40: =IF(AND(ISBLANK(D40), ISBLANK(E40), ISBLANK(G40)), "", IF(AND(E40<>"", E40=E39, D40<>"", D40=D39), B39, "PED-" & TEXT(IFERROR(VALUE(RIGHT(LOOKUP("PED-9999",$B$5:B39),4)),1000)+1, "0000"))) | C40: V-035 | F40: =IF(ISBLANK(E40),"",IFERROR(VLOOKUP(E40,'CADASTRO DE CLIENTES'!$C$6:$E$500,3,FALSE),"")) | I40: =IF(ISBLANK(G40),"",IFERROR(VLOOKUP(G40,'CADASTRO DE MATERIAL'!$C$6:$J$500,8,FALSE),"")) | J40: =IF(OR(ISBLANK(H40),ISBLANK(I40)), "", H40*I40) | L40: =IF(ISBLANK(B40), "", IF(K40="À Vista", O40, 0)) -> 0 | M40: =IF(ISBLANK(B40),"", O40 - IF(ISBLANK(L40), 0, L40)) -> 0 | O40: =IF(ISBLANK(B40),"", SUMIF($B$6:$B$500, B40, $J$6:$J$500)) -> 0 | P40: =IF(OR(ISBLANK(M40),ISBLANK(N40),N40=0), "", M40/N40)
B41: =IF(AND(ISBLANK(D41), ISBLANK(E41), ISBLANK(G41)), "", IF(AND(E41<>"", E41=E40, D41<>"", D41=D40), B40, "PED-" & TEXT(IFERROR(VALUE(RIGHT(LOOKUP("PED-9999",$B$5:B40),4)),1000)+1, "0000"))) | C41: V-036 | F41: =IF(ISBLANK(E41),"",IFERROR(VLOOKUP(E41,'CADASTRO DE CLIENTES'!$C$6:$E$500,3,FALSE),"")) | I41: =IF(ISBLANK(G41),"",IFERROR(VLOOKUP(G41,'CADASTRO DE MATERIAL'!$C$6:$J$500,8,FALSE),"")) | J41: =IF(OR(ISBLANK(H41),ISBLANK(I41)), "", H41*I41) | L41: =IF(ISBLANK(B41), "", IF(K41="À Vista", O41, 0)) -> 0 | M41: =IF(ISBLANK(B41),"", O41 - IF(ISBLANK(L41), 0, L41)) -> 0 | O41: =IF(ISBLANK(B41),"", SUMIF($B$6:$B$500, B41, $J$6:$J$500)) -> 0 | P41: =IF(OR(ISBLANK(M41),ISBLANK(N41),N41=0), "", M41/N41)
B42: =IF(AND(ISBLANK(D42), ISBLANK(E42), ISBLANK(G42)), "", IF(AND(E42<>"", E42=E41, D42<>"", D42=D41), B41, "PED-" & TEXT(IFERROR(VALUE(RIGHT(LOOKUP("PED-9999",$B$5:B41),4)),1000)+1, "0000"))) | C42: V-037 | F42: =IF(ISBLANK(E42),"",IFERROR(VLOOKUP(E42,'CADASTRO DE CLIENTES'!$C$6:$E$500,3,FALSE),"")) | I42: =IF(ISBLANK(G42),"",IFERROR(VLOOKUP(G42,'CADASTRO DE MATERIAL'!$C$6:$J$500,8,FALSE),"")) | J42: =IF(OR(ISBLANK(H42),ISBLANK(I42)), "", H42*I42) | L42: =IF(ISBLANK(B42), "", IF(K42="À Vista", O42, 0)) -> 0 | M42: =IF(ISBLANK(B42),"", O42 - IF(ISBLANK(L42), 0, L42)) -> 0 | O42: =IF(ISBLANK(B42),"", SUMIF($B$6:$B$500, B42, $J$6:$J$500)) -> 0 | P42: =IF(OR(ISBLANK(M42),ISBLANK(N42),N42=0), "", M42/N42)
B43: =IF(AND(ISBLANK(D43), ISBLANK(E43), ISBLANK(G43)), "", IF(AND(E43<>"", E43=E42, D43<>"", D43=D42), B42, "PED-" & TEXT(IFERROR(VALUE(RIGHT(LOOKUP("PED-9999",$B$5:B42),4)),1000)+1, "0000"))) | C43: V-038 | F43: =IF(ISBLANK(E43),"",IFERROR(VLOOKUP(E43,'CADASTRO DE CLIENTES'!$C$6:$E$500,3,FALSE),"")) | I43: =IF(ISBLANK(G43),"",IFERROR(VLOOKUP(G43,'CADASTRO DE MATERIAL'!$C$6:$J$500,8,FALSE),"")) | J43: =IF(OR(ISBLANK(H43),ISBLANK(I43)), "", H43*I43) | L43: =IF(ISBLANK(B43), "", IF(K43="À Vista", O43, 0)) -> 0 | M43: =IF(ISBLANK(B43),"", O43 - IF(ISBLANK(L43), 0, L43)) -> 0 | O43: =IF(ISBLANK(B43),"", SUMIF($B$6:$B$500, B43, $J$6:$J$500)) -> 0 | P43: =IF(OR(ISBLANK(M43),ISBLANK(N43),N43=0), "", M43/N43)
B44: =IF(AND(ISBLANK(D44), ISBLANK(E44), ISBLANK(G44)), "", IF(AND(E44<>"", E44=E43, D44<>"", D44=D43), B43, "PED-" & TEXT(IFERROR(VALUE(RIGHT(LOOKUP("PED-9999",$B$5:B43),4)),1000)+1, "0000"))) | C44: V-039 | F44: =IF(ISBLANK(E44),"",IFERROR(VLOOKUP(E44,'CADASTRO DE CLIENTES'!$C$6:$E$500,3,FALSE),"")) | I44: =IF(ISBLANK(G44),"",IFERROR(VLOOKUP(G44,'CADASTRO DE MATERIAL'!$C$6:$J$500,8,FALSE),"")) | J44: =IF(OR(ISBLANK(H44),ISBLANK(I44)), "", H44*I44) | L44: =IF(ISBLANK(B44), "", IF(K44="À Vista", O44, 0)) -> 0 | M44: =IF(ISBLANK(B44),"", O44 - IF(ISBLANK(L44), 0, L44)) -> 0 | O44: =IF(ISBLANK(B44),"", SUMIF($B$6:$B$500, B44, $J$6:$J$500)) -> 0 | P44: =IF(OR(ISBLANK(M44),ISBLANK(N44),N44=0), "", M44/N44)
... B500: =IF(AND(ISBLANK(D500), ISBLANK(E500), ISBLANK(G500)), "", IF(AND(E500<>"", E500=E499, D500<>"", D500=D499), B499, "PED-" & TEXT(IFERROR(VALUE(RIGHT(LOOKUP("PED-9999",$B$5:B499),4)),1000)+1, "0000"))) | C500: V-495 | F500: =IF(ISBLANK(E500),"",IFERROR(VLOOKUP(E500,'CADASTRO DE CLIENTES'!$C$6:$E$500,3,FALSE),"")) | I500: =IF(ISBLANK(G500),"",IFERROR(VLOOKUP(G500,'CADASTRO DE MATERIAL'!$C$6:$J$500,8,FALSE),"")) | J500: =IF(OR(ISBLANK(H500),ISBLANK(I500)), "", H500*I500) | L500: =IF(ISBLANK(B500), "", IF(K500="À Vista", O500, 0)) -> 0 | M500: =IF(ISBLANK(B500),"", O500 - IF(ISBLANK(L500), 0, L500)) -> 0 | O500: =IF(ISBLANK(B500),"", SUMIF($B$6:$B$500, B500, $J$6:$J$500)) -> 0 | P500: =IF(OR(ISBLANK(M500),ISBLANK(N500),N500=0), "", M500/N500)

Sheet CONTROLE DE PARCELAS
B2: CONTROLE DE PARCELAS & BAIXAS DE RECEBIMENTO
B3: Vencimentos automáticos e cálculo de Atrasado automático comparando a data atual (HOJE/TODAY) com o vencimento.
B4: PENDENTE A RECEBER: | I4: =SUMIF(K6:K1500, "Pendente", J6:J1500) -> 1839.7 | J4: ATRASADO: | K4: =SUMIF(K6:K1500, "Atrasado", J6:J1500) -> 0 | L4: TOTAL QUITADO: | M4: =SUMIF(K6:K1500, "Pago", J6:J1500) -> 0
B5: Nº Pedido | C5: Data Venda (Auto) | D5: Nome do Cliente (Auto) | E5: Telefone (Auto) | F5: Resumo / Itens do Pedido (Auto) | G5: Condição (Auto) | H5: Nº da Parcela | I5: Vencimento (+30d Auto) | J5: Valor da Parcela (R$) (Auto) | K5: Status Pagamento | L5: Data do Pagamento / Baixa | M5: Observações
B6: PED-1001 | C6: =IFERROR(VLOOKUP(B6,'SAÍDA DE VENDAS'!$B$6:$P$500,3,FALSE),"") -> 46298 | D6: =IFERROR(VLOOKUP(B6,'SAÍDA DE VENDAS'!$B$6:$P$500,4,FALSE),"") -> ADRIANA PEDRO | E6: =IFERROR(VLOOKUP(B6,'SAÍDA DE VENDAS'!$B$6:$P$500,5,FALSE),"") -> 18 99818-0064 | F6: =IF(OR(ISBLANK(B6),B6=""), "", IFERROR(INDEX('SAÍDA DE VENDAS'!$H$6:$H$500 & "x " & 'SAÍDA DE VENDAS'!$G$6:$G$500, MATCH(B6, 'SAÍDA DE VENDAS'!$B$6:$B$500, 0)), "")& IF(COUNTIF('SAÍDA DE VENDAS'!$B$6:$B$500, B6)>1, " + " & IFERROR(INDEX('SAÍDA DE VENDAS'!$H$6:$H$500 & "x " & 'SAÍDA DE VENDAS'!$G$6:$G$500, MATCH(B6, 'SAÍDA DE VENDAS'!$B$6:$B$500, 0)+1), ""), "")& IF(COUNTIF('SAÍDA DE VENDAS'!$B$6:$B$500, B6)>2, " + " & IFERROR(INDEX('SAÍDA DE VENDAS'!$H$6:$H$500 & "x " & 'SAÍDA DE VENDAS'!$G$6:$G$500, MATCH(B6, 'SAÍDA DE VENDAS'!$B$6:$B$500, 0)+2), ""), "")& IF(COUNTIF('SAÍDA DE VENDAS'!$B$6:$B$500, B6)>3, " + " & IFERROR(INDEX('SAÍDA DE VENDAS'!$H$6:$H$500 & "x " & 'SAÍDA DE VENDAS'!$G$6:$G$500, MATCH(B6, 'SAÍDA DE VENDAS'!$B$6:$B$500, 0)+3), ""), "")& IF(COUNTIF('SAÍDA DE VENDAS'!$B$6:$B$500, B6)>4, " + " & IFERROR(INDEX('SAÍDA DE VENDAS'!$H$6:$H$500 & "x " & 'SAÍDA DE VENDAS'!$G$6:$G$500, MATCH(B6, 'SAÍDA DE VENDAS'!$B$6:$B$500, 0)+4), ""), "")& IF(COUNTIF('SAÍDA DE VENDAS'!$B$6:$B$500, B6)>5, " + " & IFERROR(INDEX('SAÍDA DE VENDAS'!$H$6:$H$500 & "x " & 'SAÍDA DE VENDAS'!$G$6:$G$500, MATCH(B6, 'SAÍDA DE VENDAS'!$B$6:$B$500, 0)+5), ""), "")) -> 1x KIT LENÇOL KING 2000 FIOS 3 PEÇAS | G6: =IFERROR(VLOOKUP(B6,'SAÍDA DE VENDAS'!$B$6:$P$500,10,FALSE),"") -> À Vista | H6: 1/1 | I6: =IF(OR(ISBLANK(B6), B6="", C6=""), "", C6 + (IFERROR(VALUE(LEFT(H6, FIND("/", H6)-1)), 1) * 30)) -> 46328 | J6: =IFERROR(VLOOKUP(B6,'SAÍDA DE VENDAS'!$B$6:$P$500,15,FALSE),"") -> 0 | K6: =IF(B6="","", IF(OR(G6="À Vista", L6<>""), "Pago", IF(AND(I6<>"", I6<TODAY()), "Atrasado", "Pendente"))) -> Pago
B7: =IF(B6="","", IF(VALUE(LEFT(H6,FIND("/",H6)-1)) < VALUE(RIGHT(H6,LEN(H6)-FIND("/",H6))), B6, IFERROR(INDEX('SAÍDA DE VENDAS'!$B$6:$B$500, MATCH(B6,'SAÍDA DE VENDAS'!$B$6:$B$500,0)+COUNTIF('SAÍDA DE VENDAS'!$B$6:$B$500, B6)),""))) -> PED-1002 | C7: =IFERROR(VLOOKUP(B7,'SAÍDA DE VENDAS'!$B$6:$P$500,3,FALSE),"") -> 46298 | D7: =IFERROR(VLOOKUP(B7,'SAÍDA DE VENDAS'!$B$6:$P$500,4,FALSE),"") -> VALERIA ALVES | E7: =IFERROR(VLOOKUP(B7,'SAÍDA DE VENDAS'!$B$6:$P$500,5,FALSE),"") -> 18 93500-1704 | F7: =IF(OR(ISBLANK(B7),B7=""), "", IFERROR(INDEX('SAÍDA DE VENDAS'!$H$6:$H$500 & "x " & 'SAÍDA DE VENDAS'!$G$6:$G$500, MATCH(B7, 'SAÍDA DE VENDAS'!$B$6:$B$500, 0)), "")& IF(COUNTIF('SAÍDA DE VENDAS'!$B$6:$B$500, B7)>1, " + " & IFERROR(INDEX('SAÍDA DE VENDAS'!$H$6:$H$500 & "x " & 'SAÍDA DE VENDAS'!$G$6:$G$500, MATCH(B7, 'SAÍDA DE VENDAS'!$B$6:$B$500, 0)+1), ""), "")& IF(COUNTIF('SAÍDA DE VENDAS'!$B$6:$B$500, B7)>2, " + " & IFERROR(INDEX('SAÍDA DE VENDAS'!$H$6:$H$500 & "x " & 'SAÍDA DE VENDAS'!$G$6:$G$500, MATCH(B7, 'SAÍDA DE VENDAS'!$B$6:$B$500, 0)+2), ""), "")& IF(COUNTIF('SAÍDA DE VENDAS'!$B$6:$B$500, B7)>3, " + " & IFERROR(INDEX('SAÍDA DE VENDAS'!$H$6:$H$500 & "x " & 'SAÍDA DE VENDAS'!$G$6:$G$500, MATCH(B7, 'SAÍDA DE VENDAS'!$B$6:$B$500, 0)+3), ""), "")& IF(COUNTIF('SAÍDA DE VENDAS'!$B$6:$B$500, B7)>4, " + " & IFERROR(INDEX('SAÍDA DE VENDAS'!$H$6:$H$500 & "x " & 'SAÍDA DE VENDAS'!$G$6:$G$500, MATCH(B7, 'SAÍDA DE VENDAS'!$B$6:$B$500, 0)+4), ""), "")& IF(COUNTIF('SAÍDA DE VENDAS'!$B$6:$B$500, B7)>5, " + " & IFERROR(INDEX('SAÍDA DE VENDAS'!$H$6:$H$500 & "x " & 'SAÍDA DE VENDAS'!$G$6:$G$500, MATCH(B7, 'SAÍDA DE VENDAS'!$B$6:$B$500, 0)+5), ""), "")) -> 1x MANTA KING ALGODAO 2,45X2,85 | G7: =IFERROR(VLOOKUP(B7,'SAÍDA DE VENDAS'!$B$6:$P$500,10,FALSE),"") -> À Vista | H7: =IF(OR(ISBLANK(B7),B7=""), "", IF(B7=B6, (VALUE(LEFT(H6,FIND("/",H6)-1))+1)&"/"&RIGHT(H6,LEN(H6)-FIND("/",H6)), "1/"&IFERROR(VLOOKUP(B7,'SAÍDA DE VENDAS'!$B$6:$P$500,13,FALSE),"1"))) -> 1/1 | I7: =IF(OR(ISBLANK(B7), B7="", C7=""), "", C7 + (IFERROR(VALUE(LEFT(H7, FIND("/", H7)-1)), 1) * 30)) -> 46328 | J7: =IFERROR(VLOOKUP(B7,'SAÍDA DE VENDAS'!$B$6:$P$500,15,FALSE),"") -> 0 | K7: =IF(B7="","", IF(OR(G7="À Vista", L7<>""), "Pago", IF(AND(I7<>"", I7<TODAY()), "Atrasado", "Pendente"))) -> Pago
B8: =IF(B7="","", IF(VALUE(LEFT(H7,FIND("/",H7)-1)) < VALUE(RIGHT(H7,LEN(H7)-FIND("/",H7))), B7, IFERROR(INDEX('SAÍDA DE VENDAS'!$B$6:$B$500, MATCH(B7,'SAÍDA DE VENDAS'!$B$6:$B$500,0)+COUNTIF('SAÍDA DE VENDAS'!$B$6:$B$500, B7)),""))) -> PED-1003 | C8: =IFERROR(VLOOKUP(B8,'SAÍDA DE VENDAS'!$B$6:$P$500,3,FALSE),"") -> 46298 | D8: =IFERROR(VLOOKUP(B8,'SAÍDA DE VENDAS'!$B$6:$P$500,4,FALSE),"") -> FLAVIA BEZERRA | E8: =IFERROR(VLOOKUP(B8,'SAÍDA DE VENDAS'!$B$6:$P$500,5,FALSE),"") -> 18 99745-2150 | F8: =IF(OR(ISBLANK(B8),B8=""), "", IFERROR(INDEX('SAÍDA DE VENDAS'!$H$6:$H$500 & "x " & 'SAÍDA DE VENDAS'!$G$6:$G$500, MATCH(B8, 'SAÍDA DE VENDAS'!$B$6:$B$500, 0)), "")& IF(COUNTIF('SAÍDA DE VENDAS'!$B$6:$B$500, B8)>1, " + " & IFERROR(INDEX('SAÍDA DE VENDAS'!$H$6:$H$500 & "x " & 'SAÍDA DE VENDAS'!$G$6:$G$500, MATCH(B8, 'SAÍDA DE VENDAS'!$B$6:$B$500, 0)+1), ""), "")& IF(COUNTIF('SAÍDA DE VENDAS'!$B$6:$B$500, B8)>2, " + " & IFERROR(INDEX('SAÍDA DE VENDAS'!$H$6:$H$500 & "x " & 'SAÍDA DE VENDAS'!$G$6:$G$500, MATCH(B8, 'SAÍDA DE VENDAS'!$B$6:$B$500, 0)+2), ""), "")& IF(COUNTIF('SAÍDA DE VENDAS'!$B$6:$B$500, B8)>3, " + " & IFERROR(INDEX('SAÍDA DE VENDAS'!$H$6:$H$500 & "x " & 'SAÍDA DE VENDAS'!$G$6:$G$500, MATCH(B8, 'SAÍDA DE VENDAS'!$B$6:$B$500, 0)+3), ""), "")& IF(COUNTIF('SAÍDA DE VENDAS'!$B$6:$B$500, B8)>4, " + " & IFERROR(INDEX('SAÍDA DE VENDAS'!$H$6:$H$500 & "x " & 'SAÍDA DE VENDAS'!$G$6:$G$500, MATCH(B8, 'SAÍDA DE VENDAS'!$B$6:$B$500, 0)+4), ""), "")& IF(COUNTIF('SAÍDA DE VENDAS'!$B$6:$B$500, B8)>5, " + " & IFERROR(INDEX('SAÍDA DE VENDAS'!$H$6:$H$500 & "x " & 'SAÍDA DE VENDAS'!$G$6:$G$500, MATCH(B8, 'SAÍDA DE VENDAS'!$B$6:$B$500, 0)+5), ""), "")) -> 1x PASSADEIRA PIPOQUINHA 50X2,0 | G8: =IFERROR(VLOOKUP(B8,'SAÍDA DE VENDAS'!$B$6:$P$500,10,FALSE),"") -> À Vista | H8: =IF(OR(ISBLANK(B8),B8=""), "", IF(B8=B7, (VALUE(LEFT(H7,FIND("/",H7)-1))+1)&"/"&RIGHT(H7,LEN(H7)-FIND("/",H7)), "1/"&IFERROR(VLOOKUP(B8,'SAÍDA DE VENDAS'!$B$6:$P$500,13,FALSE),"1"))) -> 1/1 | I8: =IF(OR(ISBLANK(B8), B8="", C8=""), "", C8 + (IFERROR(VALUE(LEFT(H8, FIND("/", H8)-1)), 1) * 30)) -> 46328 | J8: =IFERROR(VLOOKUP(B8,'SAÍDA DE VENDAS'!$B$6:$P$500,15,FALSE),"") -> 0 | K8: =IF(B8="","", IF(OR(G8="À Vista", L8<>""), "Pago", IF(AND(I8<>"", I8<TODAY()), "Atrasado", "Pendente"))) -> Pago
B9: =IF(B8="","", IF(VALUE(LEFT(H8,FIND("/",H8)-1)) < VALUE(RIGHT(H8,LEN(H8)-FIND("/",H8))), B8, IFERROR(INDEX('SAÍDA DE VENDAS'!$B$6:$B$500, MATCH(B8,'SAÍDA DE VENDAS'!$B$6:$B$500,0)+COUNTIF('SAÍDA DE VENDAS'!$B$6:$B$500, B8)),""))) -> PED-1004 | C9: =IFERROR(VLOOKUP(B9,'SAÍDA DE VENDAS'!$B$6:$P$500,3,FALSE),"") -> 46300 | D9: =IFERROR(VLOOKUP(B9,'SAÍDA DE VENDAS'!$B$6:$P$500,4,FALSE),"") -> TELMA CAMPARI | E9: =IFERROR(VLOOKUP(B9,'SAÍDA DE VENDAS'!$B$6:$P$500,5,FALSE),"") -> 18 99800-5512 | F9: =IF(OR(ISBLANK(B9),B9=""), "", IFERROR(INDEX('SAÍDA DE VENDAS'!$H$6:$H$500 & "x " & 'SAÍDA DE VENDAS'!$G$6:$G$500, MATCH(B9, 'SAÍDA DE VENDAS'!$B$6:$B$500, 0)), "")& IF(COUNTIF('SAÍDA DE VENDAS'!$B$6:$B$500, B9)>1, " + " & IFERROR(INDEX('SAÍDA DE VENDAS'!$H$6:$H$500 & "x " & 'SAÍDA DE VENDAS'!$G$6:$G$500, MATCH(B9, 'SAÍDA DE VENDAS'!$B$6:$B$500, 0)+1), ""), "")& IF(COUNTIF('SAÍDA DE VENDAS'!$B$6:$B$500, B9)>2, " + " & IFERROR(INDEX('SAÍDA DE VENDAS'!$H$6:$H$500 & "x " & 'SAÍDA DE VENDAS'!$G$6:$G$500, MATCH(B9, 'SAÍDA DE VENDAS'!$B$6:$B$500, 0)+2), ""), "")& IF(COUNTIF('SAÍDA DE VENDAS'!$B$6:$B$500, B9)>3, " + " & IFERROR(INDEX('SAÍDA DE VENDAS'!$H$6:$H$500 & "x " & 'SAÍDA DE VENDAS'!$G$6:$G$500, MATCH(B9, 'SAÍDA DE VENDAS'!$B$6:$B$500, 0)+3), ""), "")& IF(COUNTIF('SAÍDA DE VENDAS'!$B$6:$B$500, B9)>4, " + " & IFERROR(INDEX('SAÍDA DE VENDAS'!$H$6:$H$500 & "x " & 'SAÍDA DE VENDAS'!$G$6:$G$500, MATCH(B9, 'SAÍDA DE VENDAS'!$B$6:$B$500, 0)+4), ""), "")& IF(COUNTIF('SAÍDA DE VENDAS'!$B$6:$B$500, B9)>5, " + " & IFERROR(INDEX('SAÍDA DE VENDAS'!$H$6:$H$500 & "x " & 'SAÍDA DE VENDAS'!$G$6:$G$500, MATCH(B9, 'SAÍDA DE VENDAS'!$B$6:$B$500, 0)+5), ""), "")) -> 1x MANTA SOFT CASAL SIMPLES | G9: =IFERROR(VLOOKUP(B9,'SAÍDA DE VENDAS'!$B$6:$P$500,10,FALSE),"") -> A Prazo | H9: =IF(OR(ISBLANK(B9),B9=""), "", IF(B9=B8, (VALUE(LEFT(H8,FIND("/",H8)-1))+1)&"/"&RIGHT(H8,LEN(H8)-FIND("/",H8)), "1/"&IFERROR(VLOOKUP(B9,'SAÍDA DE VENDAS'!$B$6:$P$500,13,FALSE),"1"))) -> 1/1 | I9: =IF(OR(ISBLANK(B9), B9="", C9=""), "", C9 + (IFERROR(VALUE(LEFT(H9, FIND("/", H9)-1)), 1) * 30)) -> 46330 | J9: =IFERROR(VLOOKUP(B9,'SAÍDA DE VENDAS'!$B$6:$P$500,15,FALSE),"") -> 39.9 | K9: =IF(B9="","", IF(OR(G9="À Vista", L9<>""), "Pago", IF(AND(I9<>"", I9<TODAY()), "Atrasado", "Pendente"))) -> Pendente
B10: =IF(B9="","", IF(VALUE(LEFT(H9,FIND("/",H9)-1)) < VALUE(RIGHT(H9,LEN(H9)-FIND("/",H9))), B9, IFERROR(INDEX('SAÍDA DE VENDAS'!$B$6:$B$500, MATCH(B9,'SAÍDA DE VENDAS'!$B$6:$B$500,0)+COUNTIF('SAÍDA DE VENDAS'!$B$6:$B$500, B9)),""))) -> PED-1005 | C10: =IFERROR(VLOOKUP(B10,'SAÍDA DE VENDAS'!$B$6:$P$500,3,FALSE),"") -> 46300 | D10: =IFERROR(VLOOKUP(B10,'SAÍDA DE VENDAS'!$B$6:$P$500,4,FALSE),"") -> ADRIANA PEDRO | E10: =IFERROR(VLOOKUP(B10,'SAÍDA DE VENDAS'!$B$6:$P$500,5,FALSE),"") -> 18 99818-0064 | F10: =IF(OR(ISBLANK(B10),B10=""), "", IFERROR(INDEX('SAÍDA DE VENDAS'!$H$6:$H$500 & "x " & 'SAÍDA DE VENDAS'!$G$6:$G$500, MATCH(B10, 'SAÍDA DE VENDAS'!$B$6:$B$500, 0)), "")& IF(COUNTIF('SAÍDA DE VENDAS'!$B$6:$B$500, B10)>1, " + " & IFERROR(INDEX('SAÍDA DE VENDAS'!$H$6:$H$500 & "x " & 'SAÍDA DE VENDAS'!$G$6:$G$500, MATCH(B10, 'SAÍDA DE VENDAS'!$B$6:$B$500, 0)+1), ""), "")& IF(COUNTIF('SAÍDA DE VENDAS'!$B$6:$B$500, B10)>2, " + " & IFERROR(INDEX('SAÍDA DE VENDAS'!$H$6:$H$500 & "x " & 'SAÍDA DE VENDAS'!$G$6:$G$500, MATCH(B10, 'SAÍDA DE VENDAS'!$B$6:$B$500, 0)+2), ""), "")& IF(COUNTIF('SAÍDA DE VENDAS'!$B$6:$B$500, B10)>3, " + " & IFERROR(INDEX('SAÍDA DE VENDAS'!$H$6:$H$500 & "x " & 'SAÍDA DE VENDAS'!$G$6:$G$500, MATCH(B10, 'SAÍDA DE VENDAS'!$B$6:$B$500, 0)+3), ""), "")& IF(COUNTIF('SAÍDA DE VENDAS'!$B$6:$B$500, B10)>4, " + " & IFERROR(INDEX('SAÍDA DE VENDAS'!$H$6:$H$500 & "x " & 'SAÍDA DE VENDAS'!$G$6:$G$500, MATCH(B10, 'SAÍDA DE VENDAS'!$B$6:$B$500, 0)+4), ""), "")& IF(COUNTIF('SAÍDA DE VENDAS'!$B$6:$B$500, B10)>5, " + " & IFERROR(INDEX('SAÍDA DE VENDAS'!$H$6:$H$500 & "x " & 'SAÍDA DE VENDAS'!$G$6:$G$500, MATCH(B10, 'SAÍDA DE VENDAS'!$B$6:$B$500, 0)+5), ""), "")) -> 2x MANTA SOFT CASAL SIMPLES | G10: =IFERROR(VLOOKUP(B10,'SAÍDA DE VENDAS'!$B$6:$P$500,10,FALSE),"") -> À Vista | H10: =IF(OR(ISBLANK(B10),B10=""), "", IF(B10=B9, (VALUE(LEFT(H9,FIND("/",H9)-1))+1)&"/"&RIGHT(H9,LEN(H9)-FIND("/",H9)), "1/"&IFERROR(VLOOKUP(B10,'SAÍDA DE VENDAS'!$B$6:$P$500,13,FALSE),"1"))) -> 1/1 | I10: =IF(OR(ISBLANK(B10), B10="", C10=""), "", C10 + (IFERROR(VALUE(LEFT(H10, FIND("/", H10)-1)), 1) * 30)) -> 46330 | J10: =IFERROR(VLOOKUP(B10,'SAÍDA DE VENDAS'!$B$6:$P$500,15,FALSE),"") -> 0 | K10: =IF(B10="","", IF(OR(G10="À Vista", L10<>""), "Pago", IF(AND(I10<>"", I10<TODAY()), "Atrasado", "Pendente"))) -> Pago
B11: =IF(B10="","", IF(VALUE(LEFT(H10,FIND("/",H10)-1)) < VALUE(RIGHT(H10,LEN(H10)-FIND("/",H10))), B10, IFERROR(INDEX('SAÍDA DE VENDAS'!$B$6:$B$500, MATCH(B10,'SAÍDA DE VENDAS'!$B$6:$B$500,0)+COUNTIF('SAÍDA DE VENDAS'!$B$6:$B$500, B10)),""))) -> PED-1006 | C11: =IFERROR(VLOOKUP(B11,'SAÍDA DE VENDAS'!$B$6:$P$500,3,FALSE),"") -> 46300 | D11: =IFERROR(VLOOKUP(B11,'SAÍDA DE VENDAS'!$B$6:$P$500,4,FALSE),"") -> LUCIA HELENA | E11: =IFERROR(VLOOKUP(B11,'SAÍDA DE VENDAS'!$B$6:$P$500,5,FALSE),"") -> 18 98205-2963 | F11: =IF(OR(ISBLANK(B11),B11=""), "", IFERROR(INDEX('SAÍDA DE VENDAS'!$H$6:$H$500 & "x " & 'SAÍDA DE VENDAS'!$G$6:$G$500, MATCH(B11, 'SAÍDA DE VENDAS'!$B$6:$B$500, 0)), "")& IF(COUNTIF('SAÍDA DE VENDAS'!$B$6:$B$500, B11)>1, " + " & IFERROR(INDEX('SAÍDA DE VENDAS'!$H$6:$H$500 & "x " & 'SAÍDA DE VENDAS'!$G$6:$G$500, MATCH(B11, 'SAÍDA DE VENDAS'!$B$6:$B$500, 0)+1), ""), "")& IF(COUNTIF('SAÍDA DE VENDAS'!$B$6:$B$500, B11)>2, " + " & IFERROR(INDEX('SAÍDA DE VENDAS'!$H$6:$H$500 & "x " & 'SAÍDA DE VENDAS'!$G$6:$G$500, MATCH(B11, 'SAÍDA DE VENDAS'!$B$6:$B$500, 0)+2), ""), "")& IF(COUNTIF('SAÍDA DE VENDAS'!$B$6:$B$500, B11)>3, " + " & IFERROR(INDEX('SAÍDA DE VENDAS'!$H$6:$H$500 & "x " & 'SAÍDA DE VENDAS'!$G$6:$G$500, MATCH(B11, 'SAÍDA DE VENDAS'!$B$6:$B$500, 0)+3), ""), "")& IF(COUNTIF('SAÍDA DE VENDAS'!$B$6:$B$500, B11)>4, " + " & IFERROR(INDEX('SAÍDA DE VENDAS'!$H$6:$H$500 & "x " & 'SAÍDA DE VENDAS'!$G$6:$G$500, MATCH(B11, 'SAÍDA DE VENDAS'!$B$6:$B$500, 0)+4), ""), "")& IF(COUNTIF('SAÍDA DE VENDAS'!$B$6:$B$500, B11)>5, " + " & IFERROR(INDEX('SAÍDA DE VENDAS'!$H$6:$H$500 & "x " & 'SAÍDA DE VENDAS'!$G$6:$G$500, MATCH(B11, 'SAÍDA DE VENDAS'!$B$6:$B$500, 0)+5), ""), "")) -> 2x MANTA SOFT CASAL SIMPLES | G11: =IFERROR(VLOOKUP(B11,'SAÍDA DE VENDAS'!$B$6:$P$500,10,FALSE),"") -> A Prazo | H11: =IF(OR(ISBLANK(B11),B11=""), "", IF(B11=B10, (VALUE(LEFT(H10,FIND("/",H10)-1))+1)&"/"&RIGHT(H10,LEN(H10)-FIND("/",H10)), "1/"&IFERROR(VLOOKUP(B11,'SAÍDA DE VENDAS'!$B$6:$P$500,13,FALSE),"1"))) -> 1/1 | I11: =IF(OR(ISBLANK(B11), B11="", C11=""), "", C11 + (IFERROR(VALUE(LEFT(H11, FIND("/", H11)-1)), 1) * 30)) -> 46330 | J11: =IFERROR(VLOOKUP(B11,'SAÍDA DE VENDAS'!$B$6:$P$500,15,FALSE),"") -> 79.8 | K11: =IF(B11="","", IF(OR(G11="À Vista", L11<>""), "Pago", IF(AND(I11<>"", I11<TODAY()), "Atrasado", "Pendente"))) -> Pendente
B12: =IF(B11="","", IF(VALUE(LEFT(H11,FIND("/",H11)-1)) < VALUE(RIGHT(H11,LEN(H11)-FIND("/",H11))), B11, IFERROR(INDEX('SAÍDA DE VENDAS'!$B$6:$B$500, MATCH(B11,'SAÍDA DE VENDAS'!$B$6:$B$500,0)+COUNTIF('SAÍDA DE VENDAS'!$B$6:$B$500, B11)),""))) -> PED-1007 | C12: =IFERROR(VLOOKUP(B12,'SAÍDA DE VENDAS'!$B$6:$P$500,3,FALSE),"") -> 46300 | D12: =IFERROR(VLOOKUP(B12,'SAÍDA DE VENDAS'!$B$6:$P$500,4,FALSE),"") -> CLAUDIA SILVA | E12: =IFERROR(VLOOKUP(B12,'SAÍDA DE VENDAS'!$B$6:$P$500,5,FALSE),"") -> 0 | F12: =IF(OR(ISBLANK(B12),B12=""), "", IFERROR(INDEX('SAÍDA DE VENDAS'!$H$6:$H$500 & "x " & 'SAÍDA DE VENDAS'!$G$6:$G$500, MATCH(B12, 'SAÍDA DE VENDAS'!$B$6:$B$500, 0)), "")& IF(COUNTIF('SAÍDA DE VENDAS'!$B$6:$B$500, B12)>1, " + " & IFERROR(INDEX('SAÍDA DE VENDAS'!$H$6:$H$500 & "x " & 'SAÍDA DE VENDAS'!$G$6:$G$500, MATCH(B12, 'SAÍDA DE VENDAS'!$B$6:$B$500, 0)+1), ""), "")& IF(COUNTIF('SAÍDA DE VENDAS'!$B$6:$B$500, B12)>2, " + " & IFERROR(INDEX('SAÍDA DE VENDAS'!$H$6:$H$500 & "x " & 'SAÍDA DE VENDAS'!$G$6:$G$500, MATCH(B12, 'SAÍDA DE VENDAS'!$B$6:$B$500, 0)+2), ""), "")& IF(COUNTIF('SAÍDA DE VENDAS'!$B$6:$B$500, B12)>3, " + " & IFERROR(INDEX('SAÍDA DE VENDAS'!$H$6:$H$500 & "x " & 'SAÍDA DE VENDAS'!$G$6:$G$500, MATCH(B12, 'SAÍDA DE VENDAS'!$B$6:$B$500, 0)+3), ""), "")& IF(COUNTIF('SAÍDA DE VENDAS'!$B$6:$B$500, B12)>4, " + " & IFERROR(INDEX('SAÍDA DE VENDAS'!$H$6:$H$500 & "x " & 'SAÍDA DE VENDAS'!$G$6:$G$500, MATCH(B12, 'SAÍDA DE VENDAS'!$B$6:$B$500, 0)+4), ""), "")& IF(COUNTIF('SAÍDA DE VENDAS'!$B$6:$B$500, B12)>5, " + " & IFERROR(INDEX('SAÍDA DE VENDAS'!$H$6:$H$500 & "x " & 'SAÍDA DE VENDAS'!$G$6:$G$500, MATCH(B12, 'SAÍDA DE VENDAS'!$B$6:$B$500, 0)+5), ""), "")) -> 1x PASSADEIRA SEDA 2 | G12: =IFERROR(VLOOKUP(B12,'SAÍDA DE VENDAS'!$B$6:$P$500,10,FALSE),"") -> A Prazo | H12: =IF(OR(ISBLANK(B12),B12=""), "", IF(B12=B11, (VALUE(LEFT(H11,FIND("/",H11)-1))+1)&"/"&RIGHT(H11,LEN(H11)-FIND("/",H11)), "1/"&IFERROR(VLOOKUP(B12,'SAÍDA DE VENDAS'!$B$6:$P$500,13,FALSE),"1"))) -> 1/1 | I12: =IF(OR(ISBLANK(B12), B12="", C12=""), "", C12 + (IFERROR(VALUE(LEFT(H12, FIND("/", H12)-1)), 1) * 30)) -> 46330 | J12: =IFERROR(VLOOKUP(B12,'SAÍDA DE VENDAS'!$B$6:$P$500,15,FALSE),"") -> 239.9 | K12: =IF(B12="","", IF(OR(G12="À Vista", L12<>""), "Pago", IF(AND(I12<>"", I12<TODAY()), "Atrasado", "Pendente"))) -> Pendente
B13: =IF(B12="","", IF(VALUE(LEFT(H12,FIND("/",H12)-1)) < VALUE(RIGHT(H12,LEN(H12)-FIND("/",H12))), B12, IFERROR(INDEX('SAÍDA DE VENDAS'!$B$6:$B$500, MATCH(B12,'SAÍDA DE VENDAS'!$B$6:$B$500,0)+COUNTIF('SAÍDA DE VENDAS'!$B$6:$B$500, B12)),""))) -> PED-1008 | C13: =IFERROR(VLOOKUP(B13,'SAÍDA DE VENDAS'!$B$6:$P$500,3,FALSE),"") -> 46301 | D13: =IFERROR(VLOOKUP(B13,'SAÍDA DE VENDAS'!$B$6:$P$500,4,FALSE),"") -> SONIA MARIA | E13: =IFERROR(VLOOKUP(B13,'SAÍDA DE VENDAS'!$B$6:$P$500,5,FALSE),"") -> 0 | F13: =IF(OR(ISBLANK(B13),B13=""), "", IFERROR(INDEX('SAÍDA DE VENDAS'!$H$6:$H$500 & "x " & 'SAÍDA DE VENDAS'!$G$6:$G$500, MATCH(B13, 'SAÍDA DE VENDAS'!$B$6:$B$500, 0)), "")& IF(COUNTIF('SAÍDA DE VENDAS'!$B$6:$B$500, B13)>1, " + " & IFERROR(INDEX('SAÍDA DE VENDAS'!$H$6:$H$500 & "x " & 'SAÍDA DE VENDAS'!$G$6:$G$500, MATCH(B13, 'SAÍDA DE VENDAS'!$B$6:$B$500, 0)+1), ""), "")& IF(COUNTIF('SAÍDA DE VENDAS'!$B$6:$B$500, B13)>2, " + " & IFERROR(INDEX('SAÍDA DE VENDAS'!$H$6:$H$500 & "x " & 'SAÍDA DE VENDAS'!$G$6:$G$500, MATCH(B13, 'SAÍDA DE VENDAS'!$B$6:$B$500, 0)+2), ""), "")& IF(COUNTIF('SAÍDA DE VENDAS'!$B$6:$B$500, B13)>3, " + " & IFERROR(INDEX('SAÍDA DE VENDAS'!$H$6:$H$500 & "x " & 'SAÍDA DE VENDAS'!$G$6:$G$500, MATCH(B13, 'SAÍDA DE VENDAS'!$B$6:$B$500, 0)+3), ""), "")& IF(COUNTIF('SAÍDA DE VENDAS'!$B$6:$B$500, B13)>4, " + " & IFERROR(INDEX('SAÍDA DE VENDAS'!$H$6:$H$500 & "x " & 'SAÍDA DE VENDAS'!$G$6:$G$500, MATCH(B13, 'SAÍDA DE VENDAS'!$B$6:$B$500, 0)+4), ""), "")& IF(COUNTIF('SAÍDA DE VENDAS'!$B$6:$B$500, B13)>5, " + " & IFERROR(INDEX('SAÍDA DE VENDAS'!$H$6:$H$500 & "x " & 'SAÍDA DE VENDAS'!$G$6:$G$500, MATCH(B13, 'SAÍDA DE VENDAS'!$B$6:$B$500, 0)+5), ""), "")) -> 1x TOALHA DE CHA 90X90 | G13: =IFERROR(VLOOKUP(B13,'SAÍDA DE VENDAS'!$B$6:$P$500,10,FALSE),"") -> A Prazo | H13: =IF(OR(ISBLANK(B13),B13=""), "", IF(B13=B12, (VALUE(LEFT(H12,FIND("/",H12)-1))+1)&"/"&RIGHT(H12,LEN(H12)-FIND("/",H12)), "1/"&IFERROR(VLOOKUP(B13,'SAÍDA DE VENDAS'!$B$6:$P$500,13,FALSE),"1"))) -> 1/1 | I13: =IF(OR(ISBLANK(B13), B13="", C13=""), "", C13 + (IFERROR(VALUE(LEFT(H13, FIND("/", H13)-1)), 1) * 30)) -> 46331 | J13: =IFERROR(VLOOKUP(B13,'SAÍDA DE VENDAS'!$B$6:$P$500,15,FALSE),"") -> 39.9 | K13: =IF(B13="","", IF(OR(G13="À Vista", L13<>""), "Pago", IF(AND(I13<>"", I13<TODAY()), "Atrasado", "Pendente"))) -> Pendente
B14: =IF(B13="","", IF(VALUE(LEFT(H13,FIND("/",H13)-1)) < VALUE(RIGHT(H13,LEN(H13)-FIND("/",H13))), B13, IFERROR(INDEX('SAÍDA DE VENDAS'!$B$6:$B$500, MATCH(B13,'SAÍDA DE VENDAS'!$B$6:$B$500,0)+COUNTIF('SAÍDA DE VENDAS'!$B$6:$B$500, B13)),""))) -> PED-1009 | C14: =IFERROR(VLOOKUP(B14,'SAÍDA DE VENDAS'!$B$6:$P$500,3,FALSE),"") -> 46301 | D14: =IFERROR(VLOOKUP(B14,'SAÍDA DE VENDAS'!$B$6:$P$500,4,FALSE),"") -> ROSE GALDINO | E14: =IFERROR(VLOOKUP(B14,'SAÍDA DE VENDAS'!$B$6:$P$500,5,FALSE),"") -> 0 | F14: =IF(OR(ISBLANK(B14),B14=""), "", IFERROR(INDEX('SAÍDA DE VENDAS'!$H$6:$H$500 & "x " & 'SAÍDA DE VENDAS'!$G$6:$G$500, MATCH(B14, 'SAÍDA DE VENDAS'!$B$6:$B$500, 0)), "")& IF(COUNTIF('SAÍDA DE VENDAS'!$B$6:$B$500, B14)>1, " + " & IFERROR(INDEX('SAÍDA DE VENDAS'!$H$6:$H$500 & "x " & 'SAÍDA DE VENDAS'!$G$6:$G$500, MATCH(B14, 'SAÍDA DE VENDAS'!$B$6:$B$500, 0)+1), ""), "")& IF(COUNTIF('SAÍDA DE VENDAS'!$B$6:$B$500, B14)>2, " + " & IFERROR(INDEX('SAÍDA DE VENDAS'!$H$6:$H$500 & "x " & 'SAÍDA DE VENDAS'!$G$6:$G$500, MATCH(B14, 'SAÍDA DE VENDAS'!$B$6:$B$500, 0)+2), ""), "")& IF(COUNTIF('SAÍDA DE VENDAS'!$B$6:$B$500, B14)>3, " + " & IFERROR(INDEX('SAÍDA DE VENDAS'!$H$6:$H$500 & "x " & 'SAÍDA DE VENDAS'!$G$6:$G$500, MATCH(B14, 'SAÍDA DE VENDAS'!$B$6:$B$500, 0)+3), ""), "")& IF(COUNTIF('SAÍDA DE VENDAS'!$B$6:$B$500, B14)>4, " + " & IFERROR(INDEX('SAÍDA DE VENDAS'!$H$6:$H$500 & "x " & 'SAÍDA DE VENDAS'!$G$6:$G$500, MATCH(B14, 'SAÍDA DE VENDAS'!$B$6:$B$500, 0)+4), ""), "")& IF(COUNTIF('SAÍDA DE VENDAS'!$B$6:$B$500, B14)>5, " + " & IFERROR(INDEX('SAÍDA DE VENDAS'!$H$6:$H$500 & "x " & 'SAÍDA DE VENDAS'!$G$6:$G$500, MATCH(B14, 'SAÍDA DE VENDAS'!$B$6:$B$500, 0)+5), ""), "")) -> 1x MANTA SOFT CASAL SIMPLES | G14: =IFERROR(VLOOKUP(B14,'SAÍDA DE VENDAS'!$B$6:$P$500,10,FALSE),"") -> A Prazo | H14: =IF(OR(ISBLANK(B14),B14=""), "", IF(B14=B13, (VALUE(LEFT(H13,FIND("/",H13)-1))+1)&"/"&RIGHT(H13,LEN(H13)-FIND("/",H13)), "1/"&IFERROR(VLOOKUP(B14,'SAÍDA DE VENDAS'!$B$6:$P$500,13,FALSE),"1"))) -> 1/1 | I14: =IF(OR(ISBLANK(B14), B14="", C14=""), "", C14 + (IFERROR(VALUE(LEFT(H14, FIND("/", H14)-1)), 1) * 30)) -> 46331 | J14: =IFERROR(VLOOKUP(B14,'SAÍDA DE VENDAS'!$B$6:$P$500,15,FALSE),"") -> 39.9 | K14: =IF(B14="","", IF(OR(G14="À Vista", L14<>""), "Pago", IF(AND(I14<>"", I14<TODAY()), "Atrasado", "Pendente"))) -> Pendente
B15: =IF(B14="","", IF(VALUE(LEFT(H14,FIND("/",H14)-1)) < VALUE(RIGHT(H14,LEN(H14)-FIND("/",H14))), B14, IFERROR(INDEX('SAÍDA DE VENDAS'!$B$6:$B$500, MATCH(B14,'SAÍDA DE VENDAS'!$B$6:$B$500,0)+COUNTIF('SAÍDA DE VENDAS'!$B$6:$B$500, B14)),""))) -> PED-1010 | C15: =IFERROR(VLOOKUP(B15,'SAÍDA DE VENDAS'!$B$6:$P$500,3,FALSE),"") -> 46302 | D15: =IFERROR(VLOOKUP(B15,'SAÍDA DE VENDAS'!$B$6:$P$500,4,FALSE),"") -> ADRIANA PEDRO | E15: =IFERROR(VLOOKUP(B15,'SAÍDA DE VENDAS'!$B$6:$P$500,5,FALSE),"") -> 18 99818-0064 | F15: =IF(OR(ISBLANK(B15),B15=""), "", IFERROR(INDEX('SAÍDA DE VENDAS'!$H$6:$H$500 & "x " & 'SAÍDA DE VENDAS'!$G$6:$G$500, MATCH(B15, 'SAÍDA DE VENDAS'!$B$6:$B$500, 0)), "")& IF(COUNTIF('SAÍDA DE VENDAS'!$B$6:$B$500, B15)>1, " + " & IFERROR(INDEX('SAÍDA DE VENDAS'!$H$6:$H$500 & "x " & 'SAÍDA DE VENDAS'!$G$6:$G$500, MATCH(B15, 'SAÍDA DE VENDAS'!$B$6:$B$500, 0)+1), ""), "")& IF(COUNTIF('SAÍDA DE VENDAS'!$B$6:$B$500, B15)>2, " + " & IFERROR(INDEX('SAÍDA DE VENDAS'!$H$6:$H$500 & "x " & 'SAÍDA DE VENDAS'!$G$6:$G$500, MATCH(B15, 'SAÍDA DE VENDAS'!$B$6:$B$500, 0)+2), ""), "")& IF(COUNTIF('SAÍDA DE VENDAS'!$B$6:$B$500, B15)>3, " + " & IFERROR(INDEX('SAÍDA DE VENDAS'!$H$6:$H$500 & "x " & 'SAÍDA DE VENDAS'!$G$6:$G$500, MATCH(B15, 'SAÍDA DE VENDAS'!$B$6:$B$500, 0)+3), ""), "")& IF(COUNTIF('SAÍDA DE VENDAS'!$B$6:$B$500, B15)>4, " + " & IFERROR(INDEX('SAÍDA DE VENDAS'!$H$6:$H$500 & "x " & 'SAÍDA DE VENDAS'!$G$6:$G$500, MATCH(B15, 'SAÍDA DE VENDAS'!$B$6:$B$500, 0)+4), ""), "")& IF(COUNTIF('SAÍDA DE VENDAS'!$B$6:$B$500, B15)>5, " + " & IFERROR(INDEX('SAÍDA DE VENDAS'!$H$6:$H$500 & "x " & 'SAÍDA DE VENDAS'!$G$6:$G$500, MATCH(B15, 'SAÍDA DE VENDAS'!$B$6:$B$500, 0)+5), ""), "")) -> 1x KIT LENÇOL KING 5200 FIOS 3 PEÇAS | G15: =IFERROR(VLOOKUP(B15,'SAÍDA DE VENDAS'!$B$6:$P$500,10,FALSE),"") -> A Prazo | H15: =IF(OR(ISBLANK(B15),B15=""), "", IF(B15=B14, (VALUE(LEFT(H14,FIND("/",H14)-1))+1)&"/"&RIGHT(H14,LEN(H14)-FIND("/",H14)), "1/"&IFERROR(VLOOKUP(B15,'SAÍDA DE VENDAS'!$B$6:$P$500,13,FALSE),"1"))) -> 1/1 | I15: =IF(OR(ISBLANK(B15), B15="", C15=""), "", C15 + (IFERROR(VALUE(LEFT(H15, FIND("/", H15)-1)), 1) * 30)) -> 46332 | J15: =IFERROR(VLOOKUP(B15,'SAÍDA DE VENDAS'!$B$6:$P$500,15,FALSE),"") -> 159.9 | K15: =IF(B15="","", IF(OR(G15="À Vista", L15<>""), "Pago", IF(AND(I15<>"", I15<TODAY()), "Atrasado", "Pendente"))) -> Pendente
B16: =IF(B15="","", IF(VALUE(LEFT(H15,FIND("/",H15)-1)) < VALUE(RIGHT(H15,LEN(H15)-FIND("/",H15))), B15, IFERROR(INDEX('SAÍDA DE VENDAS'!$B$6:$B$500, MATCH(B15,'SAÍDA DE VENDAS'!$B$6:$B$500,0)+COUNTIF('SAÍDA DE VENDAS'!$B$6:$B$500, B15)),""))) -> PED-1011 | C16: =IFERROR(VLOOKUP(B16,'SAÍDA DE VENDAS'!$B$6:$P$500,3,FALSE),"") -> 46302 | D16: =IFERROR(VLOOKUP(B16,'SAÍDA DE VENDAS'!$B$6:$P$500,4,FALSE),"") -> SONIA MARIA | E16: =IFERROR(VLOOKUP(B16,'SAÍDA DE VENDAS'!$B$6:$P$500,5,FALSE),"") -> 0 | F16: =IF(OR(ISBLANK(B16),B16=""), "", IFERROR(INDEX('SAÍDA DE VENDAS'!$H$6:$H$500 & "x " & 'SAÍDA DE VENDAS'!$G$6:$G$500, MATCH(B16, 'SAÍDA DE VENDAS'!$B$6:$B$500, 0)), "")& IF(COUNTIF('SAÍDA DE VENDAS'!$B$6:$B$500, B16)>1, " + " & IFERROR(INDEX('SAÍDA DE VENDAS'!$H$6:$H$500 & "x " & 'SAÍDA DE VENDAS'!$G$6:$G$500, MATCH(B16, 'SAÍDA DE VENDAS'!$B$6:$B$500, 0)+1), ""), "")& IF(COUNTIF('SAÍDA DE VENDAS'!$B$6:$B$500, B16)>2, " + " & IFERROR(INDEX('SAÍDA DE VENDAS'!$H$6:$H$500 & "x " & 'SAÍDA DE VENDAS'!$G$6:$G$500, MATCH(B16, 'SAÍDA DE VENDAS'!$B$6:$B$500, 0)+2), ""), "")& IF(COUNTIF('SAÍDA DE VENDAS'!$B$6:$B$500, B16)>3, " + " & IFERROR(INDEX('SAÍDA DE VENDAS'!$H$6:$H$500 & "x " & 'SAÍDA DE VENDAS'!$G$6:$G$500, MATCH(B16, 'SAÍDA DE VENDAS'!$B$6:$B$500, 0)+3), ""), "")& IF(COUNTIF('SAÍDA DE VENDAS'!$B$6:$B$500, B16)>4, " + " & IFERROR(INDEX('SAÍDA DE VENDAS'!$H$6:$H$500 & "x " & 'SAÍDA DE VENDAS'!$G$6:$G$500, MATCH(B16, 'SAÍDA DE VENDAS'!$B$6:$B$500, 0)+4), ""), "")& IF(COUNTIF('SAÍDA DE VENDAS'!$B$6:$B$500, B16)>5, " + " & IFERROR(INDEX('SAÍDA DE VENDAS'!$H$6:$H$500 & "x " & 'SAÍDA DE VENDAS'!$G$6:$G$500, MATCH(B16, 'SAÍDA DE VENDAS'!$B$6:$B$500, 0)+5), ""), "")) -> 1x JOGO DE PASSADEIRA MALHA 3 PEÇAS 1,50 | G16: =IFERROR(VLOOKUP(B16,'SAÍDA DE VENDAS'!$B$6:$P$500,10,FALSE),"") -> A Prazo | H16: =IF(OR(ISBLANK(B16),B16=""), "", IF(B16=B15, (VALUE(LEFT(H15,FIND("/",H15)-1))+1)&"/"&RIGHT(H15,LEN(H15)-FIND("/",H15)), "1/"&IFERROR(VLOOKUP(B16,'SAÍDA DE VENDAS'!$B$6:$P$500,13,FALSE),"1"))) -> 1/1 | I16: =IF(OR(ISBLANK(B16), B16="", C16=""), "", C16 + (IFERROR(VALUE(LEFT(H16, FIND("/", H16)-1)), 1) * 30)) -> 46332 | J16: =IFERROR(VLOOKUP(B16,'SAÍDA DE VENDAS'!$B$6:$P$500,15,FALSE),"") -> 99.9 | K16: =IF(B16="","", IF(OR(G16="À Vista", L16<>""), "Pago", IF(AND(I16<>"", I16<TODAY()), "Atrasado", "Pendente"))) -> Pendente
B17: =IF(B16="","", IF(VALUE(LEFT(H16,FIND("/",H16)-1)) < VALUE(RIGHT(H16,LEN(H16)-FIND("/",H16))), B16, IFERROR(INDEX('SAÍDA DE VENDAS'!$B$6:$B$500, MATCH(B16,'SAÍDA DE VENDAS'!$B$6:$B$500,0)+COUNTIF('SAÍDA DE VENDAS'!$B$6:$B$500, B16)),""))) -> PED-1012 | C17: =IFERROR(VLOOKUP(B17,'SAÍDA DE VENDAS'!$B$6:$P$500,3,FALSE),"") -> 46302 | D17: =IFERROR(VLOOKUP(B17,'SAÍDA DE VENDAS'!$B$6:$P$500,4,FALSE),"") -> HADIJA | E17: =IFERROR(VLOOKUP(B17,'SAÍDA DE VENDAS'!$B$6:$P$500,5,FALSE),"") -> 0 | F17: =IF(OR(ISBLANK(B17),B17=""), "", IFERROR(INDEX('SAÍDA DE VENDAS'!$H$6:$H$500 & "x " & 'SAÍDA DE VENDAS'!$G$6:$G$500, MATCH(B17, 'SAÍDA DE VENDAS'!$B$6:$B$500, 0)), "")& IF(COUNTIF('SAÍDA DE VENDAS'!$B$6:$B$500, B17)>1, " + " & IFERROR(INDEX('SAÍDA DE VENDAS'!$H$6:$H$500 & "x " & 'SAÍDA DE VENDAS'!$G$6:$G$500, MATCH(B17, 'SAÍDA DE VENDAS'!$B$6:$B$500, 0)+1), ""), "")& IF(COUNTIF('SAÍDA DE VENDAS'!$B$6:$B$500, B17)>2, " + " & IFERROR(INDEX('SAÍDA DE VENDAS'!$H$6:$H$500 & "x " & 'SAÍDA DE VENDAS'!$G$6:$G$500, MATCH(B17, 'SAÍDA DE VENDAS'!$B$6:$B$500, 0)+2), ""), "")& IF(COUNTIF('SAÍDA DE VENDAS'!$B$6:$B$500, B17)>3, " + " & IFERROR(INDEX('SAÍDA DE VENDAS'!$H$6:$H$500 & "x " & 'SAÍDA DE VENDAS'!$G$6:$G$500, MATCH(B17, 'SAÍDA DE VENDAS'!$B$6:$B$500, 0)+3), ""), "")& IF(COUNTIF('SAÍDA DE VENDAS'!$B$6:$B$500, B17)>4, " + " & IFERROR(INDEX('SAÍDA DE VENDAS'!$H$6:$H$500 & "x " & 'SAÍDA DE VENDAS'!$G$6:$G$500, MATCH(B17, 'SAÍDA DE VENDAS'!$B$6:$B$500, 0)+4), ""), "")& IF(COUNTIF('SAÍDA DE VENDAS'!$B$6:$B$500, B17)>5, " + " & IFERROR(INDEX('SAÍDA DE VENDAS'!$H$6:$H$500 & "x " & 'SAÍDA DE VENDAS'!$G$6:$G$500, MATCH(B17, 'SAÍDA DE VENDAS'!$B$6:$B$500, 0)+5), ""), "")) -> 1x MANTA QUEEN ALGODAO 2,20X2,50 + 1x JOGO DE PASSADEIRA MALHA 3 PEÇAS 1,50 + 1x PAR TAPETE MALHA 50X80 + 1x PAR PASSADEIRA LUXO 50X1,50 + 2x TAPETE PREMIUM 50X80 | G17: =IFERROR(VLOOKUP(B17,'SAÍDA DE VENDAS'!$B$6:$P$500,10,FALSE),"") -> A Prazo | H17: =IF(OR(ISBLANK(B17),B17=""), "", IF(B17=B16, (VALUE(LEFT(H16,FIND("/",H16)-1))+1)&"/"&RIGHT(H16,LEN(H16)-FIND("/",H16)), "1/"&IFERROR(VLOOKUP(B17,'SAÍDA DE VENDAS'!$B$6:$P$500,13,FALSE),"1"))) -> 1/3 | I17: =IF(OR(ISBLANK(B17), B17="", C17=""), "", C17 + (IFERROR(VALUE(LEFT(H17, FIND("/", H17)-1)), 1) * 30)) -> 46332 | J17: =IFERROR(VLOOKUP(B17,'SAÍDA DE VENDAS'!$B$6:$P$500,15,FALSE),"") -> 167.13333 | K17: =IF(B17="","", IF(OR(G17="À Vista", L17<>""), "Pago", IF(AND(I17<>"", I17<TODAY()), "Atrasado", "Pendente"))) -> Pendente
B18: =IF(B17="","", IF(VALUE(LEFT(H17,FIND("/",H17)-1)) < VALUE(RIGHT(H17,LEN(H17)-FIND("/",H17))), B17, IFERROR(INDEX('SAÍDA DE VENDAS'!$B$6:$B$500, MATCH(B17,'SAÍDA DE VENDAS'!$B$6:$B$500,0)+COUNTIF('SAÍDA DE VENDAS'!$B$6:$B$500, B17)),""))) -> PED-1012 | C18: =IFERROR(VLOOKUP(B18,'SAÍDA DE VENDAS'!$B$6:$P$500,3,FALSE),"") -> 46302 | D18: =IFERROR(VLOOKUP(B18,'SAÍDA DE VENDAS'!$B$6:$P$500,4,FALSE),"") -> HADIJA | E18: =IFERROR(VLOOKUP(B18,'SAÍDA DE VENDAS'!$B$6:$P$500,5,FALSE),"") -> 0 | F18: =IF(OR(ISBLANK(B18),B18=""), "", IFERROR(INDEX('SAÍDA DE VENDAS'!$H$6:$H$500 & "x " & 'SAÍDA DE VENDAS'!$G$6:$G$500, MATCH(B18, 'SAÍDA DE VENDAS'!$B$6:$B$500, 0)), "")& IF(COUNTIF('SAÍDA DE VENDAS'!$B$6:$B$500, B18)>1, " + " & IFERROR(INDEX('SAÍDA DE VENDAS'!$H$6:$H$500 & "x " & 'SAÍDA DE VENDAS'!$G$6:$G$500, MATCH(B18, 'SAÍDA DE VENDAS'!$B$6:$B$500, 0)+1), ""), "")& IF(COUNTIF('SAÍDA DE VENDAS'!$B$6:$B$500, B18)>2, " + " & IFERROR(INDEX('SAÍDA DE VENDAS'!$H$6:$H$500 & "x " & 'SAÍDA DE VENDAS'!$G$6:$G$500, MATCH(B18, 'SAÍDA DE VENDAS'!$B$6:$B$500, 0)+2), ""), "")& IF(COUNTIF('SAÍDA DE VENDAS'!$B$6:$B$500, B18)>3, " + " & IFERROR(INDEX('SAÍDA DE VENDAS'!$H$6:$H$500 & "x " & 'SAÍDA DE VENDAS'!$G$6:$G$500, MATCH(B18, 'SAÍDA DE VENDAS'!$B$6:$B$500, 0)+3), ""), "")& IF(COUNTIF('SAÍDA DE VENDAS'!$B$6:$B$500, B18)>4, " + " & IFERROR(INDEX('SAÍDA DE VENDAS'!$H$6:$H$500 & "x " & 'SAÍDA DE VENDAS'!$G$6:$G$500, MATCH(B18, 'SAÍDA DE VENDAS'!$B$6:$B$500, 0)+4), ""), "")& IF(COUNTIF('SAÍDA DE VENDAS'!$B$6:$B$500, B18)>5, " + " & IFERROR(INDEX('SAÍDA DE VENDAS'!$H$6:$H$500 & "x " & 'SAÍDA DE VENDAS'!$G$6:$G$500, MATCH(B18, 'SAÍDA DE VENDAS'!$B$6:$B$500, 0)+5), ""), "")) -> 1x MANTA QUEEN ALGODAO 2,20X2,50 + 1x JOGO DE PASSADEIRA MALHA 3 PEÇAS 1,50 + 1x PAR TAPETE MALHA 50X80 + 1x PAR PASSADEIRA LUXO 50X1,50 + 2x TAPETE PREMIUM 50X80 | G18: =IFERROR(VLOOKUP(B18,'SAÍDA DE VENDAS'!$B$6:$P$500,10,FALSE),"") -> A Prazo | H18: =IF(OR(ISBLANK(B18),B18=""), "", IF(B18=B17, (VALUE(LEFT(H17,FIND("/",H17)-1))+1)&"/"&RIGHT(H17,LEN(H17)-FIND("/",H17)), "1/"&IFERROR(VLOOKUP(B18,'SAÍDA DE VENDAS'!$B$6:$P$500,13,FALSE),"1"))) -> 2/3 | I18: =IF(OR(ISBLANK(B18), B18="", C18=""), "", C18 + (IFERROR(VALUE(LEFT(H18, FIND("/", H18)-1)), 1) * 30)) -> 46362 | J18: =IFERROR(VLOOKUP(B18,'SAÍDA DE VENDAS'!$B$6:$P$500,15,FALSE),"") -> 167.13333 | K18: =IF(B18="","", IF(OR(G18="À Vista", L18<>""), "Pago", IF(AND(I18<>"", I18<TODAY()), "Atrasado", "Pendente"))) -> Pendente
... B1499: =IF(B1498="","", IF(VALUE(LEFT(H1498,FIND("/",H1498)-1)) < VALUE(RIGHT(H1498,LEN(H1498)-FIND("/",H1498))), B1498, IFERROR(INDEX('SAÍDA DE VENDAS'!$B$6:$B$500, MATCH(B1498,'SAÍDA DE VENDAS'!$B$6:$B$500,0)+COUNTIF('SAÍDA DE VENDAS'!$B$6:$B$500, B1498)),""))) | C1499: =IFERROR(VLOOKUP(B1499,'SAÍDA DE VENDAS'!$B$6:$P$500,3,FALSE),"") -> 0 | D1499: =IFERROR(VLOOKUP(B1499,'SAÍDA DE VENDAS'!$B$6:$P$500,4,FALSE),"") -> 0 | E1499: =IFERROR(VLOOKUP(B1499,'SAÍDA DE VENDAS'!$B$6:$P$500,5,FALSE),"") | F1499: =IF(OR(ISBLANK(B1499),B1499=""), "", IFERROR(INDEX('SAÍDA DE VENDAS'!$H$6:$H$500 & "x " & 'SAÍDA DE VENDAS'!$G$6:$G$500, MATCH(B1499, 'SAÍDA DE VENDAS'!$B$6:$B$500, 0)), "")& IF(COUNTIF('SAÍDA DE VENDAS'!$B$6:$B$500, B1499)>1, " + " & IFERROR(INDEX('SAÍDA DE VENDAS'!$H$6:$H$500 & "x " & 'SAÍDA DE VENDAS'!$G$6:$G$500, MATCH(B1499, 'SAÍDA DE VENDAS'!$B$6:$B$500, 0)+1), ""), "")& IF(COUNTIF('SAÍDA DE VENDAS'!$B$6:$B$500, B1499)>2, " + " & IFERROR(INDEX('SAÍDA DE VENDAS'!$H$6:$H$500 & "x " & 'SAÍDA DE VENDAS'!$G$6:$G$500, MATCH(B1499, 'SAÍDA DE VENDAS'!$B$6:$B$500, 0)+2), ""), "")& IF(COUNTIF('SAÍDA DE VENDAS'!$B$6:$B$500, B1499)>3, " + " & IFERROR(INDEX('SAÍDA DE VENDAS'!$H$6:$H$500 & "x " & 'SAÍDA DE VENDAS'!$G$6:$G$500, MATCH(B1499, 'SAÍDA DE VENDAS'!$B$6:$B$500, 0)+3), ""), "")& IF(COUNTIF('SAÍDA DE VENDAS'!$B$6:$B$500, B1499)>4, " + " & IFERROR(INDEX('SAÍDA DE VENDAS'!$H$6:$H$500 & "x " & 'SAÍDA DE VENDAS'!$G$6:$G$500, MATCH(B1499, 'SAÍDA DE VENDAS'!$B$6:$B$500, 0)+4), ""), "")& IF(COUNTIF('SAÍDA DE VENDAS'!$B$6:$B$500, B1499)>5, " + " & IFERROR(INDEX('SAÍDA DE VENDAS'!$H$6:$H$500 & "x " & 'SAÍDA DE VENDAS'!$G$6:$G$500, MATCH(B1499, 'SAÍDA DE VENDAS'!$B$6:$B$500, 0)+5), ""), "")) | G1499: =IFERROR(VLOOKUP(B1499,'SAÍDA DE VENDAS'!$B$6:$P$500,10,FALSE),"") -> 0 | H1499: =IF(OR(ISBLANK(B1499),B1499=""), "", IF(B1499=B1498, (VALUE(LEFT(H1498,FIND("/",H1498)-1))+1)&"/"&RIGHT(H1498,LEN(H1498)-FIND("/",H1498)), "1/"&IFERROR(VLOOKUP(B1499,'SAÍDA DE VENDAS'!$B$6:$P$500,13,FALSE),"1"))) | I1499: =IF(OR(ISBLANK(B1499), B1499="", C1499=""), "", C1499 + (IFERROR(VALUE(LEFT(H1499, FIND("/", H1499)-1)), 1) * 30)) | J1499: =IFERROR(VLOOKUP(B1499,'SAÍDA DE VENDAS'!$B$6:$P$500,15,FALSE),"") | K1499: =IF(B1499="","", IF(OR(G1499="À Vista", L1499<>""), "Pago", IF(AND(I1499<>"", I1499<TODAY()), "Atrasado", "Pendente")))

Sheet CLIENTES EM ATRASO (DASHBOARD)
B2: PAINEL DE CONTAS A RECEBER POR CLIENTE
B3: Lista consolidada automática de clientes com parcelas vencidas. Conforme você dá baixa no Controle de Parcelas, o valor diminui e o cliente some ao quitar.
B4: TOTAL GERAL EM ATRASO: | E4: =SUM(E6:E100) -> 0
B5: Nome do Cliente | C5: Telefone | D5: Qtd Parc. Em Atraso | E5: Valor Em Atraso (R$) | F5: Qtd Parc. A Vencer | G5: Valor A Vencer (R$) | H5: Total a Receber (R$)
B6: ADRIANA PEDRO | C6: =IFERROR(VLOOKUP(B6, 'CADASTRO DE CLIENTES'!$C$6:$E$500, 3, FALSE), "") -> 18 99818-0064 | D6: =COUNTIFS('CONTROLE DE PARCELAS'!$D$6:$D$1500, B6, 'CONTROLE DE PARCELAS'!$K$6:$K$1500, "Atrasado") -> 0 | E6: =SUMIFS('CONTROLE DE PARCELAS'!$J$6:$J$1500, 'CONTROLE DE PARCELAS'!$D$6:$D$1500, B6, 'CONTROLE DE PARCELAS'!$K$6:$K$1500, "Atrasado") -> 0 | F6: =COUNTIFS('CONTROLE DE PARCELAS'!$D$6:$D$1500, B6, 'CONTROLE DE PARCELAS'!$K$6:$K$1500, "Pendente") -> 1 | G6: =SUMIFS('CONTROLE DE PARCELAS'!$J$6:$J$1500, 'CONTROLE DE PARCELAS'!$D$6:$D$1500, B6, 'CONTROLE DE PARCELAS'!$K$6:$K$1500, "Pendente") -> 159.9 | H6: =E6+G6 -> 159.9
B7: VALERIA ALVES | C7: =IFERROR(VLOOKUP(B7, 'CADASTRO DE CLIENTES'!$C$6:$E$500, 3, FALSE), "") -> 18 93500-1704 | D7: =COUNTIFS('CONTROLE DE PARCELAS'!$D$6:$D$1500, B7, 'CONTROLE DE PARCELAS'!$K$6:$K$1500, "Atrasado") -> 0 | E7: =SUMIFS('CONTROLE DE PARCELAS'!$J$6:$J$1500, 'CONTROLE DE PARCELAS'!$D$6:$D$1500, B7, 'CONTROLE DE PARCELAS'!$K$6:$K$1500, "Atrasado") -> 0 | F7: =COUNTIFS('CONTROLE DE PARCELAS'!$D$6:$D$1500, B7, 'CONTROLE DE PARCELAS'!$K$6:$K$1500, "Pendente") -> 0 | G7: =SUMIFS('CONTROLE DE PARCELAS'!$J$6:$J$1500, 'CONTROLE DE PARCELAS'!$D$6:$D$1500, B7, 'CONTROLE DE PARCELAS'!$K$6:$K$1500, "Pendente") -> 0 | H7: =E7+G7 -> 0
B8: FLAVIA BEZERRA | C8: =IFERROR(VLOOKUP(B8, 'CADASTRO DE CLIENTES'!$C$6:$E$500, 3, FALSE), "") -> 18 99745-2150 | D8: =COUNTIFS('CONTROLE DE PARCELAS'!$D$6:$D$1500, B8, 'CONTROLE DE PARCELAS'!$K$6:$K$1500, "Atrasado") -> 0 | E8: =SUMIFS('CONTROLE DE PARCELAS'!$J$6:$J$1500, 'CONTROLE DE PARCELAS'!$D$6:$D$1500, B8, 'CONTROLE DE PARCELAS'!$K$6:$K$1500, "Atrasado") -> 0 | F8: =COUNTIFS('CONTROLE DE PARCELAS'!$D$6:$D$1500, B8, 'CONTROLE DE PARCELAS'!$K$6:$K$1500, "Pendente") -> 0 | G8: =SUMIFS('CONTROLE DE PARCELAS'!$J$6:$J$1500, 'CONTROLE DE PARCELAS'!$D$6:$D$1500, B8, 'CONTROLE DE PARCELAS'!$K$6:$K$1500, "Pendente") -> 0 | H8: =E8+G8 -> 0
B9: TELMA CAMPARI | C9: =IFERROR(VLOOKUP(B9, 'CADASTRO DE CLIENTES'!$C$6:$E$500, 3, FALSE), "") -> 18 99800-5512 | D9: =COUNTIFS('CONTROLE DE PARCELAS'!$D$6:$D$1500, B9, 'CONTROLE DE PARCELAS'!$K$6:$K$1500, "Atrasado") -> 0 | E9: =SUMIFS('CONTROLE DE PARCELAS'!$J$6:$J$1500, 'CONTROLE DE PARCELAS'!$D$6:$D$1500, B9, 'CONTROLE DE PARCELAS'!$K$6:$K$1500, "Atrasado") -> 0 | F9: =COUNTIFS('CONTROLE DE PARCELAS'!$D$6:$D$1500, B9, 'CONTROLE DE PARCELAS'!$K$6:$K$1500, "Pendente") -> 1 | G9: =SUMIFS('CONTROLE DE PARCELAS'!$J$6:$J$1500, 'CONTROLE DE PARCELAS'!$D$6:$D$1500, B9, 'CONTROLE DE PARCELAS'!$K$6:$K$1500, "Pendente") -> 39.9 | H9: =E9+G9 -> 39.9
B10: LUCIA HELENA | C10: =IFERROR(VLOOKUP(B10, 'CADASTRO DE CLIENTES'!$C$6:$E$500, 3, FALSE), "") -> 18 98205-2963 | D10: =COUNTIFS('CONTROLE DE PARCELAS'!$D$6:$D$1500, B10, 'CONTROLE DE PARCELAS'!$K$6:$K$1500, "Atrasado") -> 0 | E10: =SUMIFS('CONTROLE DE PARCELAS'!$J$6:$J$1500, 'CONTROLE DE PARCELAS'!$D$6:$D$1500, B10, 'CONTROLE DE PARCELAS'!$K$6:$K$1500, "Atrasado") -> 0 | F10: =COUNTIFS('CONTROLE DE PARCELAS'!$D$6:$D$1500, B10, 'CONTROLE DE PARCELAS'!$K$6:$K$1500, "Pendente") -> 2 | G10: =SUMIFS('CONTROLE DE PARCELAS'!$J$6:$J$1500, 'CONTROLE DE PARCELAS'!$D$6:$D$1500, B10, 'CONTROLE DE PARCELAS'!$K$6:$K$1500, "Pendente") -> 149.7 | H10: =E10+G10 -> 149.7
B11: CLAUDIA SILVA | C11: =IFERROR(VLOOKUP(B11, 'CADASTRO DE CLIENTES'!$C$6:$E$500, 3, FALSE), "") -> 0 | D11: =COUNTIFS('CONTROLE DE PARCELAS'!$D$6:$D$1500, B11, 'CONTROLE DE PARCELAS'!$K$6:$K$1500, "Atrasado") -> 0 | E11: =SUMIFS('CONTROLE DE PARCELAS'!$J$6:$J$1500, 'CONTROLE DE PARCELAS'!$D$6:$D$1500, B11, 'CONTROLE DE PARCELAS'!$K$6:$K$1500, "Atrasado") -> 0 | F11: =COUNTIFS('CONTROLE DE PARCELAS'!$D$6:$D$1500, B11, 'CONTROLE DE PARCELAS'!$K$6:$K$1500, "Pendente") -> 1 | G11: =SUMIFS('CONTROLE DE PARCELAS'!$J$6:$J$1500, 'CONTROLE DE PARCELAS'!$D$6:$D$1500, B11, 'CONTROLE DE PARCELAS'!$K$6:$K$1500, "Pendente") -> 239.9 | H11: =E11+G11 -> 239.9
B12: SONIA MARIA | C12: =IFERROR(VLOOKUP(B12, 'CADASTRO DE CLIENTES'!$C$6:$E$500, 3, FALSE), "") -> 0 | D12: =COUNTIFS('CONTROLE DE PARCELAS'!$D$6:$D$1500, B12, 'CONTROLE DE PARCELAS'!$K$6:$K$1500, "Atrasado") -> 0 | E12: =SUMIFS('CONTROLE DE PARCELAS'!$J$6:$J$1500, 'CONTROLE DE PARCELAS'!$D$6:$D$1500, B12, 'CONTROLE DE PARCELAS'!$K$6:$K$1500, "Atrasado") -> 0 | F12: =COUNTIFS('CONTROLE DE PARCELAS'!$D$6:$D$1500, B12, 'CONTROLE DE PARCELAS'!$K$6:$K$1500, "Pendente") -> 3 | G12: =SUMIFS('CONTROLE DE PARCELAS'!$J$6:$J$1500, 'CONTROLE DE PARCELAS'!$D$6:$D$1500, B12, 'CONTROLE DE PARCELAS'!$K$6:$K$1500, "Pendente") -> 209.7 | H12: =E12+G12 -> 209.7
B13: ROSE GALDINO | C13: =IFERROR(VLOOKUP(B13, 'CADASTRO DE CLIENTES'!$C$6:$E$500, 3, FALSE), "") -> 0 | D13: =COUNTIFS('CONTROLE DE PARCELAS'!$D$6:$D$1500, B13, 'CONTROLE DE PARCELAS'!$K$6:$K$1500, "Atrasado") -> 0 | E13: =SUMIFS('CONTROLE DE PARCELAS'!$J$6:$J$1500, 'CONTROLE DE PARCELAS'!$D$6:$D$1500, B13, 'CONTROLE DE PARCELAS'!$K$6:$K$1500, "Atrasado") -> 0 | F13: =COUNTIFS('CONTROLE DE PARCELAS'!$D$6:$D$1500, B13, 'CONTROLE DE PARCELAS'!$K$6:$K$1500, "Pendente") -> 2 | G13: =SUMIFS('CONTROLE DE PARCELAS'!$J$6:$J$1500, 'CONTROLE DE PARCELAS'!$D$6:$D$1500, B13, 'CONTROLE DE PARCELAS'!$K$6:$K$1500, "Pendente") -> 169.8 | H13: =E13+G13 -> 169.8
B14: HADIJA | C14: =IFERROR(VLOOKUP(B14, 'CADASTRO DE CLIENTES'!$C$6:$E$500, 3, FALSE), "") -> 0 | D14: =COUNTIFS('CONTROLE DE PARCELAS'!$D$6:$D$1500, B14, 'CONTROLE DE PARCELAS'!$K$6:$K$1500, "Atrasado") -> 0 | E14: =SUMIFS('CONTROLE DE PARCELAS'!$J$6:$J$1500, 'CONTROLE DE PARCELAS'!$D$6:$D$1500, B14, 'CONTROLE DE PARCELAS'!$K$6:$K$1500, "Atrasado") -> 0 | F14: =COUNTIFS('CONTROLE DE PARCELAS'!$D$6:$D$1500, B14, 'CONTROLE DE PARCELAS'!$K$6:$K$1500, "Pendente") -> 3 | G14: =SUMIFS('CONTROLE DE PARCELAS'!$J$6:$J$1500, 'CONTROLE DE PARCELAS'!$D$6:$D$1500, B14, 'CONTROLE DE PARCELAS'!$K$6:$K$1500, "Pendente") -> 501.4 | H14: =E14+G14 -> 501.4
B15: TOTAL GERAL | C15: =IFERROR(VLOOKUP(B15, 'CADASTRO DE CLIENTES'!$C$6:$E$500, 3, FALSE), "") | D15: =SUM(D6:D14) -> 0 | E15: =SUM(E6:E14) -> 0 | F15: =SUM(F6:F14) -> 13 | G15: =SUM(G6:G14) -> 1470.3 | H15: =SUM(H6:H14) -> 1470.3
